Workbook

Sheet Saldo
C3: Alimentação Casa | D3: Alimentação Fora | E3: Combustivel | F3: Viagens | G3: Saídas | H3: Outros | I3: Renda+ALGT | J3: Total | K3: Rend | L3: Lucro | M3: Lucro | P3: Rendimentos: | Q3: =K16 -> 14400.64
B4: Janeiro | C4: =Janeiro!B33 -> 75.39 | D4: =Janeiro!C33 -> 154.65 | E4: =Janeiro!D33 -> 70 | F4: =Janeiro!E33 -> 10 | G4: =Janeiro!F33 -> 58 | H4: =Janeiro!G33 -> 207.33 | I4: =SUM(Janeiro!K2:L2) -> 257.7 | J4: =SUM($C4:$I4) -> 833.07 | K4: =Janeiro!L13 -> 916.5 | L4: =Janeiro!L16 -> 83.43 | M4: =L4*100/K4/100 -> 0.091031097 | P4: Despesas: | Q4: =J16 -> 9099.97
B5: Fevereiro | C5: =Fevereiro!B33 -> 107.24 | D5: =Fevereiro!C33 -> 56.2 | E5: =Fevereiro!D33 -> 30 | F5: =Fevereiro!E33 -> 39.75 | G5: =Fevereiro!F33 -> 126.2 | H5: =Fevereiro!G33 -> 429.81 | I5: =SUM(Fevereiro!K2:L2) -> 260 | J5: =SUM($C5:$I5) -> 1049.2 | K5: =Fevereiro!L13 -> 1042.28 | L5: =Fevereiro!L16 -> -6.92 | M5: =L5*100/K5/100 -> -0.0066392908 | P5: Saldo: | Q5: =Q3-Q4 -> 5300.67
B6: Março | C6: =Março!B33 -> 147.58 | D6: =Março!C33 -> 15.85 | E6: =Março!D33 -> 50 | F6: =Março!E33 -> 20 | G6: =Março!F33 -> 2 | H6: =Março!G33 -> 199.81 | I6: =SUM(Março!K2:L2) -> 262 | J6: =SUM($C6:$I6) -> 697.24 | K6: =Março!L13 -> 917.5 | L6: =Março!L16 -> 220.26 | M6: =L6*100/K6/100 -> 0.2400654
B7: Abril | C7: =Abril!B33 -> 87.5 | D7: =Abril!C33 -> 22.9 | E7: =Abril!D33 -> 30 | F7: =Abril!E33 -> 10 | G7: =Abril!F33 -> 0 | H7: =Abril!G33 -> 53 | I7: =SUM(Abril!K2:L2) -> 243 | J7: =SUM($C7:$I7) -> 446.4 | K7: =Abril!L13 -> 1528 | L7: =Abril!L16 -> 1081.6 | M7: =L7*100/K7/100 -> 0.7078534
B8: Maio | C8: =Maio!B33 -> 45.9 | D8: =Maio!C33 -> 21.6 | E8: =Maio!D33 -> 50 | F8: =Maio!E33 -> 20 | G8: =Maio!F33 -> 23 | H8: =Maio!G33 -> 782 | I8: =SUM(Maio!K2:L2) -> 255 | J8: =SUM($C8:$I8) -> 1197.5 | K8: =Maio!L13 -> 1076.26 | L8: =Maio!L16 -> -121.24 | M8: =L8*100/K8/100 -> -0.11264936
B9: Junho | C9: =Junho!B33 -> 103.92 | D9: =Junho!C33 -> 13.85 | E9: =Junho!D33 -> 70 | F9: =Junho!E33 -> 30 | G9: =Junho!F33 -> 43.7 | H9: =Junho!G33 -> 72.89 | I9: =SUM(Junho!K2:L2) -> 256.5 | J9: =SUM($C9:$I9) -> 590.86 | K9: =Junho!L13 -> 888.96 | L9: =Junho!L16 -> 298.1 | M9: =L9*100/K9/100 -> 0.33533567
B10: Julho | C10: =Julho!B33 -> 68.84 | D10: =Julho!C33 -> 117.75 | E10: =Julho!D33 -> 30 | F10: =Julho!E33 -> 23.7 | G10: =Julho!F33 -> 7.9 | H10: =Julho!G33 -> 158.4 | I10: =SUM(Julho!K2:L2) -> 289 | J10: =SUM($C10:$I10) -> 695.59 | K10: =Julho!L13 -> 1853 | L10: =Julho!L16 -> 1157.41 | M10: =L10*100/K10/100 -> 0.62461414
B11: Agosto | C11: =Agosto!B33 -> 75.9 | D11: =Agosto!C33 -> 213.68 | E11: =Agosto!D33 -> 70 | F11: =Agosto!E33 -> 34 | G11: =Agosto!F33 -> 26.1 | H11: =Agosto!G33 -> 0 | I11: =SUM(Agosto!K2:L2) -> 296 | J11: =SUM($C11:$I11) -> 715.68 | K11: =Agosto!L13 -> 916.5 | L11: =Agosto!L16 -> 200.82 | M11: =L11*100/K11/100 -> 0.2191162
B12: Setembro | C12: =Setembro!B33 -> 51.5 | D12: =Setembro!C33 -> 128.8 | E12: =Setembro!D33 -> 40 | F12: =Setembro!E33 -> 109.65 | G12: =Setembro!F33 -> 20 | H12: =Setembro!G33 -> 155.95 | I12: =SUM(Setembro!K2:L2) -> 302 | J12: =SUM($C12:$I12) -> 807.9 | K12: =Setembro!L13 -> 916.5 | L12: =Setembro!L16 -> 108.6 | M12: =L12*100/K12/100 -> 0.11849427
B13: Outubro | C13: =Outubro!B33 -> 32 | D13: =Outubro!C33 -> 108.53 | E13: =Outubro!D33 -> 0 | F13: =Outubro!E33 -> 26.75 | G13: =Outubro!F33 -> 25 | H13: =Outubro!G33 -> 217 | I13: =SUM(Outubro!K2:L2) -> 329.21 | J13: =SUM($C13:$I13) -> 738.49 | K13: =Outubro!L13 -> 939.5 | L13: =Outubro!L16 -> 201.01 | M13: =L13*100/K13/100 -> 0.21395423
B14: Novembro | C14: =Novembro!B33 -> 47.12 | D14: =Novembro!C33 -> 5 | E14: =Novembro!D33 -> 30 | F14: =Novembro!E33 -> 44.7 | G14: =Novembro!F33 -> 6.5 | H14: =Novembro!G33 -> 113.13 | I14: =SUM(Novembro!K2:L2) -> 335.5 | J14: =SUM($C14:$I14) -> 581.95 | K14: =Novembro!L13 -> 1890.5 | L14: =Novembro!L16 -> 1308.55 | M14: =L14*100/K14/100 -> 0.69217138
B15: Dezembro | C15: =Dezembro!B33 -> 21.84 | D15: =Dezembro!C33 -> 67.9 | E15: =Dezembro!D33 -> 20 | F15: =Dezembro!E33 -> 22 | G15: =Dezembro!F33 -> 68.2 | H15: =Dezembro!G33 -> 221.55 | I15: =SUM(Dezembro!K2:L2) -> 324.6 | J15: =SUM($C15:$I15) -> 746.09 | K15: =Dezembro!L13 -> 1515.14 | L15: =Dezembro!L16 -> 769.05 | M15: =L15*100/K15/100 -> 0.50757686
B16: Total: | C16: =SUM(C4:C15) -> 864.73 | D16: =SUM(D4:D15) -> 926.71 | E16: =SUM(E4:E15) -> 490 | F16: =SUM(F4:F15) -> 390.55 | G16: =SUM(G4:G15) -> 406.6 | H16: =SUM(H4:H15) -> 2610.87 | I16: =SUM(I4:I15) -> 3410.51 | J16: =SUM(J4:J15) -> 9099.97 | ... L16: =SUM(L4:L15) -> 5300.67 | M16: =L16*100/K16/100 -> 0.36808572
I17: =I16*100/K16/100 -> 0.23683045

Sheet Janeiro
A1: Dia | B1: Alimentação Casa | C1: Alimentação Fora | D1: Combustivel | E1: Viagens | F1: Saídas | G1: Outros | H1: Especificar Outros | I1: Total | K1: Renda | L1: ALGT
A2: 1 | I2: =SUM(B2:H2) -> 0 | K2: 217 | L2: 40.7
A3: 2 | F3: 3 | I3: =SUM(B3:H3) -> 3
A4: 3 | F4: 3 | I4: =SUM(B4:H4) -> 3
A5: 4 | F5: =2.7+3.2 -> 5.9 | I5: =SUM(B5:H5) -> 5.9
A6: 5 | D6: 30 | E6: 10 | I6: =SUM(B6:H6) -> 40
A7: 6 | B7: 5 | C7: 1.4 | I7: =SUM(B7:H7) -> 6.4
A8: 7 | I8: =SUM(B8:H8) -> 0
A9: 8 | C9: 0.6 | G9: =11.12+7.3 -> 18.42 | H9: futsal+lampadas | I9: =SUM(B9:H9) -> 19.02
A10: 9 | C10: 1.45 | G10: 8.5 | H10: joelheira | I10: =SUM(B10:H10) -> 9.95
A11: 10 | C11: 0.45 | F11: 3 | I11: =SUM(B11:H11) -> 3.45
A12: 11 | B12: =53.17-G12 -> 36.18 | F12: 3 | G12: =2.49+6+4.5+4 -> 16.99 | H12: higiene | I12: =SUM(B12:H12) -> 56.17
A13: 12 | G13: 13 | H13: ventilador | I13: =SUM(B13:H13) -> 13 | K13: Rendimentos: | L13: 916.5
A14: 13 | C14: 0.45 | I14: =SUM(B14:H14) -> 0.45 | K14: Despesas: | L14: =SUM(B33:H33)+K2+L2 -> 833.07 | M14: =L14*100/L13/100 -> 0.9089689
A15: 14 | B15: 4.8 | C15: 0.8 | I15: =SUM(B15:H15) -> 5.6
A16: 15 | C16: =0.45+0.25 -> 0.7 | G16: 50 | H16: dentista | I16: =SUM(B16:H16) -> 50.7 | K16: Saldo: | L16: =L13-L14 -> 83.43 | M16: =(L16*100/L13)/100 -> 0.091031097
A17: 16 | C17: =0.9+0.25 -> 1.15 | I17: =SUM(B17:H17) -> 1.15
A18: 17 | C18: =7.75 -> 7.75 | F18: 12.5 | I18: =SUM(B18:H18) -> 20.25
A19: 18 | I19: =SUM(B19:H19) -> 0
A20: 19 | B20: 23 | G20: 44 | H20: camisa | I20: =SUM(B20:H20) -> 67
A21: 20 | C21: =0.25+0.45 -> 0.7 | I21: =SUM(B21:H21) -> 0.7
A22: 21 | C22: 0.8 | D22: 40 | G22: =30+8.25 -> 38.25 | H22: consulta+farmacia | I22: =SUM(B22:H22) -> 79.05
A23: 22 | C23: 0.45 | F23: 10 | I23: =SUM(B23:H23) -> 10.45
A24: 23 | C24: 0.25 | I24: =SUM(B24:H24) -> 0.25
A25: 24 | C25: 17.5 | F25: =2.5+1+2 -> 5.5 | I25: =SUM(B25:H25) -> 23
A26: 25 | C26: 6.2 | F26: =6.4+5.7 -> 12.1 | I26: =SUM(B26:H26) -> 18.3
A27: 26 | H27: eco | I27: =SUM(B27:H27) -> 0
A28: 27 | B28: =12.08-2-3.67 -> 6.41 | C28: =0.45+0.25 -> 0.7 | G28: =12.5+(2+3.67) -> 18.17 | H28: eco+higien | I28: =SUM(B28:H28) -> 25.28
A29: 28 | C29: 0.6 | I29: =SUM(B29:H29) -> 0.6
A30: 29 | C30: 0.6 | I30: =SUM(B30:H30) -> 0.6
A31: 30 | C31: 0.6 | I31: =SUM(B31:H31) -> 0.6
A32: 31 | C32: 111.5 | I32: =SUM(B32:H32) -> 111.5
A33: Total | B33: =SUM(B2:B32) -> 75.39 | C33: =SUM(C2:C32) -> 154.65 | D33: =SUM(D2:D32) -> 70 | E33: =SUM(E2:E32) -> 10 | F33: =SUM(F2:F32) -> 58 | G33: =SUM(G2:G32) -> 207.33 | H33: =SUM(H2:H32) -> 0 | I33: =SUM(I2:I32) -> 575.37

Sheet Fevereiro
A1: Dia | B1: Alimentação Casa | C1: Alimentação Fora | D1: Combustivel | E1: Viagens | F1: Saídas | G1: Outros | H1: Especificar Outros | I1: Total | K1: Renda | L1: ALGT
A2: 1 | B2: 48.74 | F2: 6.4 | I2: =SUM(B2:H2) -> 55.14 | K2: 217 | L2: 43
A3: 2 | I3: =SUM(B3:H3) -> 0
A4: 3 | C4: =0.25+0.45 -> 0.7 | I4: =SUM(B4:H4) -> 0.7
A5: 4 | C5: =0.25+0.45 -> 0.7 | G5: 30 | H5: consulta | I5: =SUM(B5:H5) -> 30.7
A6: 5 | C6: =0.25+0.45 -> 0.7 | F6: 2 | I6: =SUM(B6:H6) -> 2.7
A7: 6 | B7: 1.5 | C7: =0.25+0.45 -> 0.7 | G7: =58+16.25 -> 74.25 | H7: dermo+famacia | I7: =SUM(B7:H7) -> 76.45
A8: 7 | C8: 0.7 | E8: 13.75 | F8: 3.7 | I8: =SUM(B8:H8) -> 18.15
A9: 8 | C9: 24 | F9: =1.2+1.7 -> 2.9 | I9: =SUM(B9:H9) -> 26.9
A10: 9 | E10: =13.5+2.5 -> 16 | I10: =SUM(B10:H10) -> 16
A11: 10 | C11: 0.7 | I11: =SUM(B11:H11) -> 0.7
A12: 11 | C12: 0.7 | I12: =SUM(B12:H12) -> 0.7
A13: 12 | C13: 1.3 | F13: =23.5 -> 23.5 | G13: 50 | H13: dentista | I13: =SUM(B13:H13) -> 74.8 | K13: Rendimentos: | L13: 1042.28
A14: 13 | C14: 1.3 | I14: =SUM(B14:H14) -> 1.3 | K14: Despesas: | L14: =SUM(B33:H33)+K2+L2 -> 1049.2 | M14: =L14*100/L13/100 -> 1.0066393
A15: 14 | C15: 0.7 | I15: =SUM(B15:H15) -> 0.7
A16: 15 | F16: =14+3 -> 17 | I16: =SUM(B16:H16) -> 17 | K16: Saldo: | L16: =L13-L14 -> -6.92 | M16: =(L16*100/L13)/100 -> -0.0066392908
A17: 16 | B17: 57 | I17: =SUM(B17:H17) -> 57
A18: 17 | C18: 0.7 | I18: =SUM(B18:H18) -> 0.7
A19: 18 | C19: 0.45 | G19: =30+56 -> 86 | H19: consulta+sacoor | I19: =SUM(B19:H19) -> 86.45
A20: 19 | C20: =1.1+0.25 -> 1.35 | G20: 174.56 | H20: seguro carro | I20: =SUM(B20:H20) -> 175.91
A21: 20 | C21: =0.45+8.35 -> 8.8 | I21: =SUM(B21:H21) -> 8.8
A22: 21 | C22: =0.45+0.25+4 -> 4.7 | F22: 2 | I22: =SUM(B22:H22) -> 6.7
A23: 22 | F23: 3 | I23: =SUM(B23:H23) -> 3
A24: 23 | I24: =SUM(B24:H24) -> 0
A25: 24 | C25: 0.7 | I25: =SUM(B25:H25) -> 0.7
A26: 25 | C26: 7.3 | F26: =45+12+5 -> 62 | I26: =SUM(B26:H26) -> 69.3
A27: 26 | D27: 30 | I27: =SUM(B27:H27) -> 30
A28: 27 | I28: =SUM(B28:H28) -> 0
A29: 28 | E29: 10 | F29: 3.7 | I29: =SUM(B29:H29) -> 13.7
A30: 29 | G30: 15 | H30: G12 | I30: =SUM(B30:H30) -> 15
A31: 30 | I31: =SUM(B31:H31) -> 0
A32: 31 | I32: =SUM(B32:H32) -> 0
A33: Total | B33: =SUM(B2:B32) -> 107.24 | C33: =SUM(C2:C32) -> 56.2 | D33: =SUM(D2:D32) -> 30 | E33: =SUM(E2:E32) -> 39.75 | F33: =SUM(F2:F32) -> 126.2 | G33: =SUM(G2:G32) -> 429.81 | H33: =SUM(H2:H32) -> 0 | I33: =SUM(I2:I32) -> 789.2

Sheet Março
A1: Dia | B1: Alimentação Casa | C1: Alimentação Fora | D1: Combustivel | E1: Viagens | F1: Saídas | G1: Outros | H1: Especificar Outros | I1: Total | K1: Renda | L1: ALGT
A2: 1 | I2: =SUM(B2:H2) -> 0 | K2: 217 | L2: 45
A3: 2 | D3: 20 | E3: 10 | I3: =SUM(B3:H3) -> 30
A4: 3 | C4: 0.6 | G4: 40.8 | H4: analises | I4: =SUM(B4:H4) -> 41.4
A5: 4 | C5: 1.3 | I5: =SUM(B5:H5) -> 1.3
A6: 5 | B6: 3.6 | C6: 0.45 | I6: =SUM(B6:H6) -> 4.05
A7: 6 | C7: =0.6+8.2 -> 8.8 | F7: 2 | I7: =SUM(B7:H7) -> 10.8
A8: 7 | B8: 35 | G8: 27.5 | H8: tac | I8: =SUM(B8:H8) -> 62.5
A9: 8 | I9: =SUM(B9:H9) -> 0
A10: 9 | B10: 2 | C10: =0.25+0.45+0.3 -> 1 | I10: =SUM(B10:H10) -> 3
A11: 10 | C11: 1 | I11: =SUM(B11:H11) -> 1
A12: 11 | C12: =0.25+0.45+1.1 -> 1.8 | D12: 30 | G12: 12.3 | H12: futsal | I12: =SUM(B12:H12) -> 44.1
A13: 12 | B13: 7.5 | C13: 0.45 | I13: =SUM(B13:H13) -> 7.95 | K13: Rendimentos: | L13: 917.5
A14: 13 | C14: 0.45 | I14: =SUM(B14:H14) -> 0.45 | K14: Despesas: | L14: =SUM(B33:H33)+K2+L2 -> 697.24 | M14: =L14*100/L13/100 -> 0.7599346
A15: 14 | B15: 9 | G15: 12 | H15: jg ps4 | I15: =SUM(B15:H15) -> 21
A16: 15 | B16: =97.8-G16 -> 69.71 | G16: =(3.76+3.24+2+0.33+0.59+2.47+3.77)+(1.99+0.97+3.99+3.49+1.49) -> 28.09 | I16: =SUM(B16:H16) -> 97.8 | K16: Saldo: | L16: =L13-L14 -> 220.26 | M16: =(L16*100/L13)/100 -> 0.2400654
A17: 16 | I17: =SUM(B17:H17) -> 0
A18: 17 | I18: =SUM(B18:H18) -> 0
A19: 18 | I19: =SUM(B19:H19) -> 0
A20: 19 | G20: 32.38 | H20: prozis | I20: =SUM(B20:H20) -> 32.38
A21: 20 | G21: 45 | H21: consulta | I21: =SUM(B21:H21) -> 45
A22: 21 | I22: =SUM(B22:H22) -> 0
A23: 22 | B23: 20.77 | G23: 1.74 | I23: =SUM(B23:H23) -> 22.51
A24: 23 | I24: =SUM(B24:H24) -> 0
A25: 24 | I25: =SUM(B25:H25) -> 0
A26: 25 | I26: =SUM(B26:H26) -> 0
A27: 26 | I27: =SUM(B27:H27) -> 0
A28: 27 | I28: =SUM(B28:H28) -> 0
A29: 28 | E29: 10 | I29: =SUM(B29:H29) -> 10
A30: 29 | I30: =SUM(B30:H30) -> 0
A31: 30 | I31: =SUM(B31:H31) -> 0
A32: 31 | I32: =SUM(B32:H32) -> 0
A33: Total | B33: =SUM(B2:B32) -> 147.58 | C33: =SUM(C2:C32) -> 15.85 | D33: =SUM(D2:D32) -> 50 | E33: =SUM(E2:E32) -> 20 | F33: =SUM(F2:F32) -> 2 | G33: =SUM(G2:G32) -> 199.81 | H33: =SUM(H2:H32) -> 0 | I33: =SUM(I2:I32) -> 435.24

Sheet Abril
A1: Dia | B1: Alimentação Casa | C1: Alimentação Fora | D1: Combustivel | E1: Viagens | F1: Saídas | G1: Outros | H1: Especificar Outros | I1: Total | K1: Renda | L1: ALGT
A2: 1 | I2: =SUM(B2:H2) -> 0 | K2: 217 | L2: 26
A3: 2 | I3: =SUM(B3:H3) -> 0
A4: 3 | I4: =SUM(B4:H4) -> 0
A5: 4 | I5: =SUM(B5:H5) -> 0
A6: 5 | I6: =SUM(B6:H6) -> 0
A7: 6 | I7: =SUM(B7:H7) -> 0
A8: 7 | I8: =SUM(B8:H8) -> 0
A9: 8 | G9: -1000 | H9: pai | I9: =SUM(B9:H9) -> -1000
A10: 9 | I10: =SUM(B10:H10) -> 0
A11: 10 | I11: =SUM(B11:H11) -> 0
A12: 11 | I12: =SUM(B12:H12) -> 0
A13: 12 | I13: =SUM(B13:H13) -> 0 | K13: Rendimentos: | L13: =1266+262 -> 1528
A14: 13 | D14: 30 | E14: 10 | I14: =SUM(B14:H14) -> 40 | K14: Despesas: | L14: =SUM(B33:H33)+K2+L2 -> 446.4 | M14: =L14*100/L13/100 -> 0.2921466
A15: 14 | B15: 17.5 | H15: lidl | I15: =SUM(B15:H15) -> 17.5
A16: 15 | G16: 17 | H16: tekken ps4 | I16: =SUM(B16:H16) -> 17 | K16: Saldo: | L16: =L13-L14 -> 1081.6 | M16: =(L16*100/L13)/100 -> 0.7078534
A17: 16 | I17: =SUM(B17:H17) -> 0
A18: 17 | G18: 999 | H18: pc | I18: =SUM(B18:H18) -> 999
A19: 18 | C19: =8.2+9.3 -> 17.5 | H19: vinho + francesinha | I19: =SUM(B19:H19) -> 17.5
A20: 19 | I20: =SUM(B20:H20) -> 0
A21: 20 | G21: 5 | H21: windows | I21: =SUM(B21:H21) -> 5
A22: 21 | I22: =SUM(B22:H22) -> 0
A23: 22 | I23: =SUM(B23:H23) -> 0
A24: 23 | B24: 70 | H24: continente | I24: =SUM(B24:H24) -> 70
A25: 24 | I25: =SUM(B25:H25) -> 0
A26: 25 | C26: 5.4 | I26: =SUM(B26:H26) -> 5.4
A27: 26 | I27: =SUM(B27:H27) -> 0
A28: 27 | G28: 32 | H28: prozis | I28: =SUM(B28:H28) -> 32
A29: 28 | H29: seg.social mae | I29: =SUM(B29:H29) -> 0
A30: 29 | I30: =SUM(B30:H30) -> 0
A31: 30 | I31: =SUM(B31:H31) -> 0
A32: 31 | I32: =SUM(B32:H32) -> 0
A33: Total | B33: =SUM(B2:B32) -> 87.5 | C33: =SUM(C2:C32) -> 22.9 | D33: =SUM(D2:D32) -> 30 | E33: =SUM(E2:E32) -> 10 | F33: =SUM(F2:F32) -> 0 | G33: =SUM(G2:G32) -> 53 | H33: =SUM(H2:H32) -> 0 | I33: =SUM(I2:I32) -> 203.4

Sheet Maio
A1: Dia | B1: Alimentação Casa | C1: Alimentação Fora | D1: Combustivel | E1: Viagens | F1: Saídas | G1: Outros | H1: Especificar Outros | I1: Total | K1: Renda | L1: ALGT
A2: 1 | I2: =SUM(B2:H2) -> 0 | K2: 217 | L2: 38
A3: 2 | B3: 17.1 | I3: =SUM(B3:H3) -> 17.1
A4: 3 | I4: =SUM(B4:H4) -> 0
A5: 4 | I5: =SUM(B5:H5) -> 0
A6: 5 | I6: =SUM(B6:H6) -> 0
A7: 6 | B7: 6.8 | I7: =SUM(B7:H7) -> 6.8
A8: 7 | I8: =SUM(B8:H8) -> 0
A9: 8 | D9: 30 | I9: =SUM(B9:H9) -> 30
A10: 9 | E10: 10 | G10: 730 | H10: iphone | I10: =SUM(B10:H10) -> 740
A11: 10 | I11: =SUM(B11:H11) -> 0
A12: 11 | I12: =SUM(B12:H12) -> 0
A13: 12 | I13: =SUM(B13:H13) -> 0 | K13: Rendimentos: | L13: =778.86+627.4-330 -> 1076.26 | N13: ordenado | O13: segsocial mae
A14: 13 | I14: =SUM(B14:H14) -> 0 | K14: Despesas: | L14: =SUM(B33:H33)+K2+L2 -> 1197.5 | M14: =L14*100/L13/100 -> 1.1126494
A15: 14 | H15: teleconsulta | I15: =SUM(B15:H15) -> 0
A16: 15 | C16: 8.6 | H16: francesinha | I16: =SUM(B16:H16) -> 8.6 | K16: Saldo: | L16: =L13-L14 -> -121.24 | M16: =(L16*100/L13)/100 -> -0.11264936
A17: 16 | E17: 10 | F17: 20 | H17: varios dias | I17: =SUM(B17:H17) -> 30
A18: 17 | I18: =SUM(B18:H18) -> 0
A19: 18 | I19: =SUM(B19:H19) -> 0
A20: 19 | D20: 20 | I20: =SUM(B20:H20) -> 20
A21: 20 | I21: =SUM(B21:H21) -> 0
A22: 21 | B22: 3 | G22: 30 | H22: piscina | I22: =SUM(B22:H22) -> 33
A23: 22 | I23: =SUM(B23:H23) -> 0
A24: 23 | B24: =32-C24 -> 19 | C24: 13 | G24: 22 | H24: extensor ethernet | I24: =SUM(B24:H24) -> 54
A25: 24 | I25: =SUM(B25:H25) -> 0
A26: 25 | I26: =SUM(B26:H26) -> 0
A27: 26 | I27: =SUM(B27:H27) -> 0
A28: 27 | I28: =SUM(B28:H28) -> 0
A29: 28 | I29: =SUM(B29:H29) -> 0
A30: 29 | F30: 3 | I30: =SUM(B30:H30) -> 3
A31: 30 | I31: =SUM(B31:H31) -> 0
A32: 31 | I32: =SUM(B32:H32) -> 0
A33: Total | B33: =SUM(B2:B32) -> 45.9 | C33: =SUM(C2:C32) -> 21.6 | D33: =SUM(D2:D32) -> 50 | E33: =SUM(E2:E32) -> 20 | F33: =SUM(F2:F32) -> 23 | G33: =SUM(G2:G32) -> 782 | H33: =SUM(H2:H32) -> 0 | I33: =SUM(I2:I32) -> 942.5

Sheet Junho
A1: Dia | B1: Alimentação Casa | C1: Alimentação Fora | D1: Combustivel | E1: Viagens | F1: Saídas | G1: Outros | H1: Especificar Outros | I1: Total | K1: Renda | L1: ALGT
A2: 1 | F2: 1.9 | I2: =SUM(B2:H2) -> 1.9 | K2: 217 | L2: 39.5
A3: 2 | D3: 40 | F3: 3.7 | I3: =SUM(B3:H3) -> 43.7
A4: 3 | I4: =SUM(B4:H4) -> 0
A5: 4 | I5: =SUM(B5:H5) -> 0
A6: 5 | F6: 3.7 | I6: =SUM(B6:H6) -> 3.7
A7: 6 | F7: 2.7 | I7: =SUM(B7:H7) -> 2.7
A8: 7 | E8: 10 | I8: =SUM(B8:H8) -> 10
A9: 8 | I9: =SUM(B9:H9) -> 0
A10: 9 | F10: 3 | I10: =SUM(B10:H10) -> 3
A11: 10 | B11: =(52-G11)+2.4 -> 51.4 | G11: 3 | I11: =SUM(B11:H11) -> 54.4
A12: 11 | I12: =SUM(B12:H12) -> 0
A13: 12 | B13: 6.6 | I13: =SUM(B13:H13) -> 6.6 | K13: Rendimentos: | L13: 888.96
A14: 13 | B14: 8.22 | G14: =14+9 -> 23 | H14: capas ebay+ the witcher | I14: =SUM(B14:H14) -> 31.22 | K14: Despesas: | L14: =SUM(B33:H33)+K2+L2 -> 590.86 | M14: =L14*100/L13/100 -> 0.66466433
A15: 14 | I15: =SUM(B15:H15) -> 0
A16: 15 | I16: =SUM(B16:H16) -> 0 | K16: Saldo: | L16: =L13-L14 -> 298.1 | M16: =(L16*100/L13)/100 -> 0.33533567
A17: 16 | I17: =SUM(B17:H17) -> 0
A18: 17 | B18: 0.41 | I18: =SUM(B18:H18) -> 0.41
A19: 18 | F19: 2 | I19: =SUM(B19:H19) -> 2
A20: 19 | C20: 6.7 | I20: =SUM(B20:H20) -> 6.7
A21: 20 | F21: 4 | I21: =SUM(B21:H21) -> 4
A22: 21 | F22: 4 | I22: =SUM(B22:H22) -> 4
A23: 22 | B23: 28.09 | I23: =SUM(B23:H23) -> 28.09
A24: 23 | I24: =SUM(B24:H24) -> 0
A25: 24 | I25: =SUM(B25:H25) -> 0
A26: 25 | D26: 20 | E26: 10 | F26: 4.7 | I26: =SUM(B26:H26) -> 34.7
A27: 26 | F27: =3+4+3 -> 10 | I27: =SUM(B27:H27) -> 10
A28: 27 | C28: 5.5 | D28: 10 | E28: 10 | F28: 4 | I28: =SUM(B28:H28) -> 29.5
A29: 28 | G29: =10+8.39+8.5 -> 26.89 | H29: cartao jovem+jogo steam+bilhete comboio | I29: =SUM(B29:H29) -> 26.89
A30: 29 | B30: 9.2 | C30: 1.2 | I30: =SUM(B30:H30) -> 10.4
A31: 30 | C31: 0.45 | G31: 20 | H31: prozis | I31: =SUM(B31:H31) -> 20.45
A32: 31 | I32: =SUM(B32:H32) -> 0
A33: Total | B33: =SUM(B2:B32) -> 103.92 | C33: =SUM(C2:C32) -> 13.85 | D33: =SUM(D2:D32) -> 70 | E33: =SUM(E2:E32) -> 30 | F33: =SUM(F2:F32) -> 43.7 | G33: =SUM(G2:G32) -> 72.89 | H33: =SUM(H2:H32) -> 0 | I33: =SUM(I2:I32) -> 334.36

Sheet Julho
A1: Dia | B1: Alimentação Casa | C1: Alimentação Fora | D1: Combustivel | E1: Viagens | F1: Saídas | G1: Outros | H1: Especificar Outros | I1: Total | K1: Renda | L1: ALGT
A2: 1 | C2: 0.45 | I2: =SUM(B2:H2) -> 0.45 | K2: 250 | L2: 39
A3: 2 | C3: 0.45 | I3: =SUM(B3:H3) -> 0.45
A4: 3 | C4: 0.45 | I4: =SUM(B4:H4) -> 0.45
A5: 4 | B5: 35.17 | G5: 12.9 | H5: PC 2 | I5: =SUM(B5:H5) -> 48.07
A6: 5 | I6: =SUM(B6:H6) -> 0
A7: 6 | C7: 0.45 | I7: =SUM(B7:H7) -> 0.45
A8: 7 | C8: 0.45 | I8: =SUM(B8:H8) -> 0.45
A9: 8 | C9: 0.45 | I9: =SUM(B9:H9) -> 0.45
A10: 9 | C10: 0.45 | E10: 8.5 | I10: =SUM(B10:H10) -> 8.95
A11: 10 | C11: 32 | F11: 1.2 | G11: 30 | H11: casaco e c3 | I11: =SUM(B11:H11) -> 63.2
A12: 11 | I12: =SUM(B12:H12) -> 0
A13: 12 | E13: 13.5 | F13: 1.7 | I13: =SUM(B13:H13) -> 15.2 | K13: Rendimentos: | L13: 1853
A14: 13 | C14: 0.45 | I14: =SUM(B14:H14) -> 0.45 | K14: Despesas: | L14: =SUM(B33:H33)+K2+L2 -> 695.59 | M14: =L14*100/L13/100 -> 0.37538586
A15: 14 | C15: 0.45 | G15: 115.5 | H15: oculos | I15: =SUM(B15:H15) -> 115.95
A16: 15 | B16: 21.67 | C16: 0.25 | D16: 30 | I16: =SUM(B16:H16) -> 51.92 | K16: Saldo: | L16: =L13-L14 -> 1157.41 | M16: =(L16*100/L13)/100 -> 0.62461414
A17: 16 | C17: 0.25 | I17: =SUM(B17:H17) -> 0.25
A18: 17 | C18: 8.9 | H18: uber eats- bk | I18: =SUM(B18:H18) -> 8.9
A19: 18 | I19: =SUM(B19:H19) -> 0
A20: 19 | C20: 16 | H20: mexicano | I20: =SUM(B20:H20) -> 16
A21: 20 | C21: 0.5 | I21: =SUM(B21:H21) -> 0.5
A22: 21 | C22: 0.5 | I22: =SUM(B22:H22) -> 0.5
A23: 22 | B23: 12 | C23: 0.5 | H23: cerveja | I23: =SUM(B23:H23) -> 12.5
A24: 23 | C24: 18 | F24: 5 | I24: =SUM(B24:H24) -> 23
A25: 24 | C25: 0.5 | I25: =SUM(B25:H25) -> 0.5
A26: 25 | C26: =12.5+7 -> 19.5 | E26: 1.7 | H26: guimaraes | I26: =SUM(B26:H26) -> 21.2
A27: 26 | C27: 14.3 | H27: francesinha | I27: =SUM(B27:H27) -> 14.3
A28: 27 | C28: 0.5 | I28: =SUM(B28:H28) -> 0.5
A29: 28 | C29: 0.5 | I29: =SUM(B29:H29) -> 0.5
A30: 29 | C30: 0.5 | I30: =SUM(B30:H30) -> 0.5
A31: 30 | C31: 0.5 | I31: =SUM(B31:H31) -> 0.5
A32: 31 | C32: 0.5 | G32: =48-48 -> 0 | H32: casaco | I32: =SUM(B32:H32) -> 0.5
A33: Total | B33: =SUM(B2:B32) -> 68.84 | C33: =SUM(C2:C32) -> 117.75 | D33: =SUM(D2:D32) -> 30 | E33: =SUM(E2:E32) -> 23.7 | F33: =SUM(F2:F32) -> 7.9 | G33: =SUM(G2:G32) -> 158.4 | H33: =SUM(H2:H32) -> 0 | I33: =SUM(I2:I32) -> 406.59

Sheet Agosto
A1: Dia | B1: Alimentação Casa | C1: Alimentação Fora | D1: Combustivel | E1: Viagens | F1: Saídas | G1: Outros | H1: Especificar Outros | I1: Total | K1: Renda | L1: ALGT
A2: 1 | C2: 10 | H2: dunas | I2: =SUM(B2:H2) -> 10 | K2: 250 | L2: 46
A3: 2 | C3: 25.3 | H3: c3 | I3: =SUM(B3:H3) -> 25.3
A4: 3 | C4: 30 | H4: finfas | I4: =SUM(B4:H4) -> 30
A5: 4 | C5: =22.5+23.6 -> 46.1 | E5: 10 | H5: nazare(rosa+marisco) | I5: =SUM(B5:H5) -> 56.1
A6: 5 | E6: 10 | H6: cascata e fragas | I6: =SUM(B6:H6) -> 10
A7: 6 | C7: 1.2 | F7: 1.5 | H7: Oliveiras | I7: =SUM(B7:H7) -> 2.7
A8: 7 | C8: =11.5+7 -> 18.5 | D8: 20 | F8: 4.5 | H8: vida boa+palheiro | I8: =SUM(B8:H8) -> 43
A9: 8 | F9: 5 | I9: =SUM(B9:H9) -> 5
A10: 9 | H10: joka | I10: =SUM(B10:H10) -> 0
A11: 10 | C11: 14.3 | F11: 5.4 | H11: boteco | I11: =SUM(B11:H11) -> 19.7
A12: 11 | C12: 3 | F12: 2.7 | I12: =SUM(B12:H12) -> 5.7
A13: 12 | E13: 4 | I13: =SUM(B13:H13) -> 4 | K13: Rendimentos: | L13: 916.5
A14: 13 | F14: 2 | I14: =SUM(B14:H14) -> 2 | K14: Despesas: | L14: =SUM(B33:H33)+K2+L2 -> 715.68 | M14: =L14*100/L13/100 -> 0.7808838
A15: 14 | D15: 20 | F15: 2 | I15: =SUM(B15:H15) -> 22
A16: 15 | H16: poços | I16: =SUM(B16:H16) -> 0 | K16: Saldo: | L16: =L13-L14 -> 200.82 | M16: =(L16*100/L13)/100 -> 0.2191162
A17: 16 | E17: 10 | I17: =SUM(B17:H17) -> 10
A18: 17 | B18: 42.67 | C18: 0.5 | I18: =SUM(B18:H18) -> 43.17
A19: 18 | C19: 0.5 | I19: =SUM(B19:H19) -> 0.5
A20: 19 | C20: 0.5 | I20: =SUM(B20:H20) -> 0.5
A21: 20 | C21: 0.5 | I21: =SUM(B21:H21) -> 0.5
A22: 21 | C22: 0.5 | I22: =SUM(B22:H22) -> 0.5
A23: 22 | I23: =SUM(B23:H23) -> 0
A24: 23 | B24: 5 | I24: =SUM(B24:H24) -> 5
A25: 24 | C25: 0.5 | I25: =SUM(B25:H25) -> 0.5
A26: 25 | C26: =0.5+19.78 -> 20.28 | D26: 30 | F26: 3 | H26: posta | I26: =SUM(B26:H26) -> 53.28
A27: 26 | B27: 28.23 | C27: 0.5 | I27: =SUM(B27:H27) -> 28.73
A28: 27 | C28: 0.5 | I28: =SUM(B28:H28) -> 0.5
A29: 28 | C29: 0.5 | I29: =SUM(B29:H29) -> 0.5
A30: 29 | C30: 20 | H30: ramen | I30: =SUM(B30:H30) -> 20
A31: 30 | C31: =11+9 -> 20 | H31: degema e t. do lebre | I31: =SUM(B31:H31) -> 20
A32: 31 | C32: 0.5 | I32: =SUM(B32:H32) -> 0.5
A33: Total | B33: =SUM(B2:B32) -> 75.9 | C33: =SUM(C2:C32) -> 213.68 | D33: =SUM(D2:D32) -> 70 | E33: =SUM(E2:E32) -> 34 | F33: =SUM(F2:F32) -> 26.1 | G33: =SUM(G2:G32) -> 0 | H33: =SUM(H2:H32) -> 0 | I33: =SUM(I2:I32) -> 419.68

Sheet Setembro
A1: Dia | B1: Alimentação Casa | C1: Alimentação Fora | D1: Combustivel | E1: Viagens | F1: Saídas | G1: Outros | H1: Especificar Outros | I1: Total | K1: Renda | L1: ALGT
A2: 1 | C2: 0.5 | I2: =SUM(B2:H2) -> 0.5 | K2: 250 | L2: 52
A3: 2 | C3: 1.5 | G3: 38 | H3: perfume | I3: =SUM(B3:H3) -> 39.5
A4: 3 | C4: 15 | F4: 5 | H4: tapas | I4: =SUM(B4:H4) -> 20
A5: 4 | B5: 20 | I5: =SUM(B5:H5) -> 20
A6: 5 | B6: 4 | G6: 55 | H6: m.barbear | I6: =SUM(B6:H6) -> 59
A7: 6 | E7: 5.4 | H7: fao | I7: =SUM(B7:H7) -> 5.4
A8: 7 | C8: 0.5 | I8: =SUM(B8:H8) -> 0.5
A9: 8 | C9: 0.5 | I9: =SUM(B9:H9) -> 0.5
A10: 9 | C10: 0.5 | I10: =SUM(B10:H10) -> 0.5
A11: 10 | C11: 0.5 | I11: =SUM(B11:H11) -> 0.5
A12: 11 | C12: 1 | I12: =SUM(B12:H12) -> 1
A13: 12 | B13: 5.5 | C13: 6.5 | E13: =24+27 -> 51 | G13: 5 | I13: =SUM(B13:H13) -> 68 | K13: Rendimentos: | L13: 916.5
A14: 13 | I14: =SUM(B14:H14) -> 0 | K14: Despesas: | L14: =SUM(B33:H33)+K2+L2 -> 807.9 | M14: =L14*100/L13/100 -> 0.88150573
A15: 14 | B15: 22 | D15: 40 | I15: =SUM(B15:H15) -> 62
A16: 15 | C16: 9.3 | G16: 7.95 | H16: tab | I16: =SUM(B16:H16) -> 17.25 | K16: Saldo: | L16: =L13-L14 -> 108.6 | M16: =(L16*100/L13)/100 -> 0.11849427
A17: 16 | G17: 50 | H17: dentista | I17: =SUM(B17:H17) -> 50
A18: 17 | C18: =30 -> 30 | H18: filipa | I18: =SUM(B18:H18) -> 30
A19: 18 | C19: 2 | E19: 5 | I19: =SUM(B19:H19) -> 7
A20: 19 | C20: 20 | E20: 5 | G20: 37.5 | H20: kart+faisao | I20: =SUM(B20:H20) -> 25
A21: 20 | E21: =13.5+2.5 -> 16 | I21: =SUM(B21:H21) -> 16
A22: 21 | C22: 0.5 | I22: =SUM(B22:H22) -> 0.5
A23: 22 | C23: 0.5 | I23: =SUM(B23:H23) -> 0.5
A24: 23 | C24: 0.5 | I24: =SUM(B24:H24) -> 0.5
A25: 24 | C25: 0.5 | I25: =SUM(B25:H25) -> 0.5
A26: 25 | E26: 13.75 | F26: 5 | I26: =SUM(B26:H26) -> 18.75
A27: 26 | C27: 35 | F27: =5+5 -> 10 | H27: c3 | I27: =SUM(B27:H27) -> 45
A28: 27 | E28: 13.5 | I28: =SUM(B28:H28) -> 13.5
A29: 28 | C29: 1 | I29: =SUM(B29:H29) -> 1
A30: 29 | C30: 1 | I30: =SUM(B30:H30) -> 1
A31: 30 | C31: 1 | I31: =SUM(B31:H31) -> 1
A32: 31 | C32: 1 | I32: =SUM(B32:H32) -> 1
A33: Total | B33: =SUM(B2:B32) -> 51.5 | C33: =SUM(C2:C32) -> 128.8 | D33: =SUM(D2:D32) -> 40 | E33: =SUM(E2:E32) -> 109.65 | F33: =SUM(F2:F32) -> 20 | G33: =SUM(G2:G32) -> 155.95 | H33: =SUM(H2:H32) -> 0 | I33: =SUM(I2:I32) -> 505.9

Sheet Outubro
A1: Dia | B1: Alimentação Casa | C1: Alimentação Fora | D1: Combustivel | E1: Viagens | F1: Saídas | G1: Outros | H1: Especificar Outros | I1: Total | K1: Renda | L1: ALGT
A2: 1 | C2: 1 | G2: 87.5 | H2: casaco | I2: =SUM(B2:H2) -> 88.5 | K2: 250 | L2: =66.21+12+1 -> 79.21
A3: 2 | C3: =1+39.54 -> 40.54 | I3: =SUM(B3:H3) -> 40.54
A4: 3 | I4: =SUM(B4:H4) -> 0
A5: 4 | I5: =SUM(B5:H5) -> 0
A6: 5 | C6: 1 | I6: =SUM(B6:H6) -> 1
A7: 6 | C7: 1 | I7: =SUM(B7:H7) -> 1
A8: 7 | C8: 1 | I8: =SUM(B8:H8) -> 1
A9: 8 | C9: =1.49+0.5 -> 1.99 | I9: =SUM(B9:H9) -> 1.99
A10: 9 | C10: 0.5 | I10: =SUM(B10:H10) -> 0.5
A11: 10 | B11: 25 | I11: =SUM(B11:H11) -> 25
A12: 11 | I12: =SUM(B12:H12) -> 0
A13: 12 | C13: 0.5 | I13: =SUM(B13:H13) -> 0.5 | K13: Rendimentos: | L13: 939.5
A14: 13 | C14: 0.5 | I14: =SUM(B14:H14) -> 0.5 | K14: Despesas: | L14: =SUM(B33:H33)+K2+L2 -> 738.49 | M14: =L14*100/L13/100 -> 0.78604577
A15: 14 | C15: 0.5 | G15: 50 | H15: dentista | I15: =SUM(B15:H15) -> 50.5
A16: 15 | C16: 0.5 | G16: =8.5+8 -> 16.5 | H16: olheiras+tabaco | I16: =SUM(B16:H16) -> 17 | K16: Saldo: | L16: =L13-L14 -> 201.01 | M16: =(L16*100/L13)/100 -> 0.21395423
A17: 16 | C17: 0.5 | E17: 13.75 | F17: 5 | I17: =SUM(B17:H17) -> 19.25
A18: 17 | C18: 20 | F18: 3 | I18: =SUM(B18:H18) -> 23
A19: 18 | E19: 13 | F19: 2 | I19: =SUM(B19:H19) -> 15
A20: 19 | C20: 1.25 | I20: =SUM(B20:H20) -> 1.25
A21: 20 | B21: 7 | C21: 1 | I21: =SUM(B21:H21) -> 8
A22: 21 | C22: 0.5 | I22: =SUM(B22:H22) -> 0.5
A23: 22 | C23: 0.5 | I23: =SUM(B23:H23) -> 0.5
A24: 23 | C24: 0.25 | I24: =SUM(B24:H24) -> 0.25
A25: 24 | C25: 20 | F25: 15 | I25: =SUM(B25:H25) -> 35
A26: 25 | C26: 13 | I26: =SUM(B26:H26) -> 13
A27: 26 | C27: 0.5 | G27: 63 | I27: =SUM(B27:H27) -> 63.5
A28: 27 | C28: 0.5 | I28: =SUM(B28:H28) -> 0.5
A29: 28 | C29: 0.5 | I29: =SUM(B29:H29) -> 0.5
A30: 29 | C30: 0.5 | I30: =SUM(B30:H30) -> 0.5
A31: 30 | C31: 0.5 | I31: =SUM(B31:H31) -> 0.5
A32: 31 | I32: =SUM(B32:H32) -> 0
A33: Total | B33: =SUM(B2:B32) -> 32 | C33: =SUM(C2:C32) -> 108.53 | D33: =SUM(D2:D32) -> 0 | E33: =SUM(E2:E32) -> 26.75 | F33: =SUM(F2:F32) -> 25 | G33: =SUM(G2:G32) -> 217 | H33: =SUM(H2:H32) -> 0 | I33: =SUM(I2:I32) -> 409.28

Sheet Novembro
A1: Dia | B1: Alimentação Casa | C1: Alimentação Fora | D1: Combustivel | E1: Viagens | F1: Saídas | G1: Outros | H1: Especificar Outros | I1: Total | K1: Renda | L1: ALGT
A2: 1 | B2: =37.07-G2 -> 22.54 | G2: =2.89+0.59+2.09+6.27+2.69 -> 14.53 | H2: higiene | I2: =SUM(B2:H2) -> 37.07 | K2: 250 | L2: =12+1+72.5 -> 85.5
A3: 2 | C3: 0.5 | I3: =SUM(B3:H3) -> 0.5
A4: 3 | C4: 0.5 | D4: 30 | I4: =SUM(B4:H4) -> 30.5
A5: 4 | E5: 10 | G5: 9.15 | H5: tab | I5: =SUM(B5:H5) -> 19.15
A6: 5 | I6: =SUM(B6:H6) -> 0
A7: 6 | I7: =SUM(B7:H7) -> 0
A8: 7 | F8: 1.9 | G8: 31 | H8: inspecção | I8: =SUM(B8:H8) -> 32.9
A9: 8 | F9: 1.9 | I9: =SUM(B9:H9) -> 1.9
A10: 9 | E10: =13.5+2.5 -> 16 | I10: =SUM(B10:H10) -> 16
A11: 10 | C11: 0.25 | I11: =SUM(B11:H11) -> 0.25
A12: 11 | C12: 0.25 | I12: =SUM(B12:H12) -> 0.25
A13: 12 | C13: 0.5 | I13: =SUM(B13:H13) -> 0.5 | K13: Rendimentos: | L13: 1890.5
A14: 13 | C14: 0.5 | I14: =SUM(B14:H14) -> 0.5 | K14: Despesas: | L14: =SUM(B33:H33)+K2+L2 -> 581.95 | M14: =L14*100/L13/100 -> 0.30782862
A15: 14 | I15: =SUM(B15:H15) -> 0
A16: 15 | B16: 9 | I16: =SUM(B16:H16) -> 9 | K16: Saldo: | L16: =L13-L14 -> 1308.55 | M16: =(L16*100/L13)/100 -> 0.69217138
A17: 16 | B17: 11.45 | C17: 0.5 | I17: =SUM(B17:H17) -> 11.95
A18: 17 | C18: 0.5 | I18: =SUM(B18:H18) -> 0.5
A19: 18 | C19: 0.5 | E19: 3.2 | G19: 50 | H19: dent | I19: =SUM(B19:H19) -> 53.7
A20: 19 | C20: 0.5 | I20: =SUM(B20:H20) -> 0.5
A21: 20 | C21: 0.5 | I21: =SUM(B21:H21) -> 0.5
A22: 21 | B22: 4.13 | G22: 8.45 | H22: tab | I22: =SUM(B22:H22) -> 12.58
A23: 22 | I23: =SUM(B23:H23) -> 0
A24: 23 | I24: =SUM(B24:H24) -> 0
A25: 24 | I25: =SUM(B25:H25) -> 0
A26: 25 | E26: =13+2.5 -> 15.5 | I26: =SUM(B26:H26) -> 15.5
A27: 26 | F27: 2.7 | I27: =SUM(B27:H27) -> 2.7
A28: 27 | I28: =SUM(B28:H28) -> 0
A29: 28 | I29: =SUM(B29:H29) -> 0
A30: 29 | I30: =SUM(B30:H30) -> 0
A31: 30 | I31: =SUM(B31:H31) -> 0
A32: 31 | I32: =SUM(B32:H32) -> 0
A33: Total | B33: =SUM(B2:B32) -> 47.12 | C33: =SUM(C2:C32) -> 5 | D33: =SUM(D2:D32) -> 30 | E33: =SUM(E2:E32) -> 44.7 | F33: =SUM(F2:F32) -> 6.5 | G33: =SUM(G2:G32) -> 113.13 | H33: =SUM(H2:H32) -> 0 | I33: =SUM(I2:I32) -> 246.45

Sheet Dezembro
A1: Dia | B1: Alimentação Casa | C1: Alimentação Fora | D1: Combustivel | E1: Viagens | F1: Saídas | G1: Outros | H1: Especificar Outros | I1: Total | K1: Renda | L1: ALGT
A2: 1 | I2: =SUM(B2:H2) -> 0 | K2: 250 | L2: =12+1+61.6 -> 74.6
A3: 2 | I3: =SUM(B3:H3) -> 0
A4: 3 | I4: =SUM(B4:H4) -> 0
A5: 4 | I5: =SUM(B5:H5) -> 0
A6: 5 | I6: =SUM(B6:H6) -> 0
A7: 6 | I7: =SUM(B7:H7) -> 0
A8: 7 | I8: =SUM(B8:H8) -> 0
A9: 8 | I9: =SUM(B9:H9) -> 0
A10: 9 | I10: =SUM(B10:H10) -> 0
A11: 10 | I11: =SUM(B11:H11) -> 0
A12: 11 | F12: 2.7 | G12: =5.18+4.09+3.43 -> 12.7 | H12: peliculas+carregador | I12: =SUM(B12:H12) -> 15.4
A13: 12 | G13: 8 | I13: =SUM(B13:H13) -> 8 | K13: Rendimentos: | L13: =1015.14+500 -> 1515.14
A14: 13 | E14: 12 | I14: =SUM(B14:H14) -> 12 | K14: Despesas: | L14: =SUM(B33:H33)+K2+L2 -> 746.09 | M14: =L14*100/L13/100 -> 0.49242314
A15: 14 | B15: 17.84 | G15: 8.45 | H15: tab | I15: =SUM(B15:H15) -> 26.29
A16: 15 | I16: =SUM(B16:H16) -> 0 | K16: Saldo: | L16: =L13-L14 -> 769.05 | M16: =(L16*100/L13)/100 -> 0.50757686
A17: 16 | I17: =SUM(B17:H17) -> 0
A18: 17 | G18: 52.4 | H18: compras natal | I18: =SUM(B18:H18) -> 52.4
A19: 18 | C19: 2.7 | I19: =SUM(B19:H19) -> 2.7
A20: 19 | I20: =SUM(B20:H20) -> 0
A21: 20 | I21: =SUM(B21:H21) -> 0
A22: 21 | B22: 4 | G22: 45 | H22: psn plus | I22: =SUM(B22:H22) -> 49
A23: 22 | D23: 20 | I23: =SUM(B23:H23) -> 20
A24: 23 | C24: 6.7 | E24: 10 | F24: 10 | G24: 50 | H24: dentista | I24: =SUM(B24:H24) -> 76.7
A25: 24 | G25: 45 | H25: psplus | I25: =SUM(B25:H25) -> 45
A26: 25 | F26: 5 | I26: =SUM(B26:H26) -> 5
A27: 26 | F27: 1 | I27: =SUM(B27:H27) -> 1
A28: 27 | F28: 1 | I28: =SUM(B28:H28) -> 1
A29: 28 | F29: 1 | I29: =SUM(B29:H29) -> 1
A30: 29 | C30: 31 | F30: 1 | H30: c3 | I30: =SUM(B30:H30) -> 32
A31: 30 | I31: =SUM(B31:H31) -> 0
A32: 31 | C32: 27.5 | F32: =62-15.5 -> 46.5 | I32: =SUM(B32:H32) -> 74
A33: Total | B33: =SUM(B2:B32) -> 21.84 | C33: =SUM(C2:C32) -> 67.9 | D33: =SUM(D2:D32) -> 20 | E33: =SUM(E2:E32) -> 22 | F33: =SUM(F2:F32) -> 68.2 | G33: =SUM(G2:G32) -> 221.55 | H33: =SUM(H2:H32) -> 0 | I33: =SUM(I2:I32) -> 421.49
