Workbook

Sheet template
A1: Dia | B1: Alimentação | C1: Higiene | D1: Combustivel | E1: Viagens | F1: Saídas | G1: Outros | H1: Especificar Outros | I1: Total | K1: Renda:
A2: 1 | I2: =SUM(B2:H2) -> 0 | K2: Telecomunicações:
A3: 2 | I3: =SUM(B3:H3) -> 0
A4: 3 | I4: =SUM(B4:H4) -> 0
A5: 4 | I5: =SUM(B5:H5) -> 0
A6: 5 | I6: =SUM(B6:H6) -> 0
A7: 6 | I7: =SUM(B7:H7) -> 0
A8: 7 | I8: =SUM(B8:H8) -> 0
A9: 8 | I9: =SUM(B9:H9) -> 0
A10: 9 | I10: =SUM(B10:H10) -> 0
A11: 10 | I11: =SUM(B11:H11) -> 0
A12: 11 | I12: =SUM(B12:H12) -> 0
A13: 12 | I13: =SUM(B13:H13) -> 0 | K13: Rendimentos:
A14: 13 | I14: =SUM(B14:H14) -> 0 | K14: Despesas: | L14: =SUM(B33:H33)+L1+L2 -> 0
A15: 14 | I15: =SUM(B15:H15) -> 0
A16: 15 | I16: =SUM(B16:H16) -> 0 | K16: Saldo: | L16: =L13-L14 -> 0
A17: 16 | I17: =SUM(B17:H17) -> 0
A18: 17 | I18: =SUM(B18:H18) -> 0
A19: 18 | I19: =SUM(B19:H19) -> 0
A20: 19 | I20: =SUM(B20:H20) -> 0
A21: 20 | I21: =SUM(B21:H21) -> 0
A22: 21 | I22: =SUM(B22:H22) -> 0
A23: 22 | I23: =SUM(B23:H23) -> 0
A24: 23 | I24: =SUM(B24:H24) -> 0
A25: 24 | I25: =SUM(B25:H25) -> 0
A26: 25 | I26: =SUM(B26:H26) -> 0
A27: 26 | I27: =SUM(B27:H27) -> 0
A28: 27 | I28: =SUM(B28:H28) -> 0
... A32: 31 | I32: =SUM(B32:H32) -> 0
A33: Total | B33: =SUM(B2:B32) -> 0 | C33: =SUM(C2:C32) -> 0 | D33: =SUM(D2:D32) -> 0 | E33: =SUM(E2:E32) -> 0 | F33: =SUM(F2:F32) -> 0 | G33: =SUM(G2:G32) -> 0 | H33: =SUM(H2:H32) -> 0 | I33: =SUM(I2:I32) -> 0

Sheet Saldo
C3: Alimentação | D3: Higiene | E3: Combustivel | F3: Viagens | G3: Saídas | H3: Outros | I3: Renda | J3: Total | K3: Lucro | M3: Rendimentos: | N3: =Janeiro!L13+Fevereiro!L13+Março!L13+Abril!L13+Maio!L13+Junho!L13+Julho!L13+Agosto!L13+Setembro!L13+Outubro!L13+Novembro!L13+Dezembro!L13 -> 12675.69
B4: Janeiro | C4: =Janeiro!B33 -> 83.56 | D4: =Janeiro!C33 -> 22.99 | E4: =Janeiro!D33 -> 30 | F4: =Janeiro!E33 -> 30 | G4: =Janeiro!F33 -> 20 | H4: =Janeiro!G33 -> 0 | I4: =Janeiro!L1 -> 90 | J4: =SUM(C4:I4) -> 276.55 | K4: =Janeiro!$L$16 -> 130.83 | M4: Despesas: | N4: =J16 -> 9195.49
B5: Fevereiro | C5: =Fevereiro!B33 -> 118.18 | D5: =Fevereiro!C33 -> 0 | E5: =Fevereiro!D33 -> 60 | F5: =Fevereiro!E33 -> 62.78 | G5: =Fevereiro!F33 -> 11.95 | H5: =Fevereiro!G33 -> 95.08 | I5: =Fevereiro!L1 -> 250 | J5: =SUM(C5:I5) -> 597.99 | K5: =Fevereiro!$L$16 -> 318.01 | M5: Saldo: | N5: =N3-N4 -> 3480.2
B6: Março | C6: =Março!B33 -> 117.77 | D6: =Março!C33 -> 9.79 | E6: =Março!D33 -> 80 | F6: =Março!E33 -> 58.01 | G6: =Março!F33 -> 48.55 | H6: =Março!G33 -> 102.06 | I6: =Março!L1 -> 250 | J6: =SUM(C6:I6) -> 666.18 | K6: =Março!$L$16 -> 249.82
B7: Abril | C7: =Abril!B33 -> 85.19 | D7: =Abril!C33 -> 0 | E7: =Abril!D33 -> 100 | F7: =Abril!E33 -> 58.3 | G7: =Abril!F33 -> 148.45 | H7: =Abril!G33 -> 149.46 | I7: =Abril!L1 -> 250 | J7: =SUM(C7:I7) -> 791.4 | K7: =Abril!$L$16 -> 268.6
B8: Maio | C8: =Maio!B33 -> 51.86 | D8: =Maio!C33 -> 9.31 | E8: =Maio!D33 -> 70 | F8: =Maio!E33 -> 67.38 | G8: =Maio!F33 -> 128.65 | H8: =Maio!G33 -> 68.99 | I8: =Maio!L1 -> 250 | J8: =SUM(C8:I8) -> 646.19 | K8: =Maio!$L$16 -> 300.21
B9: Junho | C9: =Junho!B33 -> 65.45 | D9: =Junho!C33 -> 0.59 | E9: =Junho!D33 -> 50 | F9: =Junho!E33 -> 48.3 | G9: =Junho!F33 -> 159.51 | H9: =Junho!G33 -> 218.95 | I9: =Junho!L1 -> 250 | J9: =SUM(C9:I9) -> 792.8 | K9: =Junho!$L$16 -> 123.7
B10: Julho | C10: =Julho!B33 -> 70.24 | D10: =Julho!C33 -> 11.3 | E10: =Julho!D33 -> 66 | F10: =Julho!E33 -> 48.2 | G10: =Julho!F33 -> 154.4 | H10: =Julho!G33 -> 161.19 | I10: =Julho!L1+Julho!L2 -> 273.5 | J10: =SUM(C10:I10) -> 784.83 | K10: =Julho!$L$16 -> 1057.32
B11: Agosto | C11: =Agosto!B33 -> 146.52 | D11: =Agosto!C33 -> 0 | E11: =Agosto!D33 -> 75 | F11: =Agosto!E33 -> 32 | G11: =Agosto!F33 -> 217.8 | H11: =Agosto!G33 -> 577.5 | I11: =Agosto!L1+Agosto!L2 -> 267.5 | J11: =SUM(C11:I11) -> 1316.32 | K11: =Agosto!$L$16 -> -399.82
B12: Setembro | C12: =Setembro!B33 -> 135.39 | D12: =Setembro!C33 -> 14.16 | E12: =Setembro!D33 -> 15 | F12: =Setembro!E33 -> 27.5 | G12: =Setembro!F33 -> 109.5 | H12: =Setembro!G33 -> 90 | I12: =Setembro!L1+Setembro!L2 -> 257 | J12: =SUM(C12:I12) -> 648.55 | K12: =Setembro!$L$16 -> 278.71
B13: Outubro | C13: =Outubro!B33 -> 117.91 | D13: =Outubro!C33 -> 8.9 | E13: =Outubro!D33 -> 90 | F13: =Outubro!E33 -> 26.6 | G13: =Outubro!F33 -> 122.6 | H13: =Outubro!G33 -> 210.19 | I13: =Outubro!L1+Outubro!L2++Outubro!L3 -> 275 | J13: =SUM(C13:I13) -> 851.2 | K13: =Outubro!$L$16 -> 64.8
B14: Novembro | C14: =Novembro!B33 -> 106.36 | D14: =Novembro!C33 -> 0 | E14: =Novembro!D33 -> 60 | F14: =Novembro!E33 -> 20 | G14: =Novembro!F33 -> 90.9 | H14: =Novembro!G33 -> 333.74 | I14: =Novembro!L1+Novembro!L2+Novembro!L3 -> 266 | J14: =SUM(C14:I14) -> 877 | K14: =Novembro!$L$16 -> 918
B15: Dezembro | C15: =Dezembro!B33 -> 100.93 | D15: =Dezembro!C33 -> 0 | E15: =Dezembro!D33 -> 20 | F15: =Dezembro!E33 -> 79.5 | G15: =Dezembro!F33 -> 146.7 | H15: =Dezembro!G33 -> 318.75 | I15: =Dezembro!L1+Dezembro!L2+Dezembro!L3 -> 280.6 | J15: =SUM(C15:I15) -> 946.48 | K15: =Dezembro!$L$16 -> 170.02
B16: Total: | C16: =SUM(C4:C15) -> 1199.36 | D16: =SUM(D4:D15) -> 77.04 | E16: =SUM(E4:E15) -> 716 | F16: =SUM(F4:F15) -> 558.57 | G16: =SUM(G4:G15) -> 1359.01 | H16: =SUM(H4:H15) -> 2325.91 | I16: =SUM(I4:I15) -> 2959.6 | J16: =SUM(C16:I16) -> 9195.49 | K16: =SUM(K4:K15) -> 3480.2

Sheet Gráficos

Sheet Janeiro
A1: Dia | B1: Alimentação | C1: Higiene | D1: Combustivel | E1: Viagens | F1: Saídas | G1: Outros | H1: Especificar Outros | K1: Renda: | L1: 90
A2: 1 | K2: Telecomunicações:
A3: 2
A4: 3
A5: 4
A6: 5
A7: 6
A8: 7
A9: 8
A10: 9
A11: 10
A12: 11
A13: 12 | K13: Rendimentos: | L13: 407.38
A14: 13 | K14: Despesas: | L14: =SUM(B33:H33)+L1+L2 -> 276.55
A15: 14
A16: 15 | K16: Saldo: | L16: =L13-L14 -> 130.83
A17: 16
A18: 17
A19: 18
A20: 19 | B20: =71.91-C20 -> 48.92 | C20: =3.11+3.39+1.84+3.24+1.79+5.99+1.79+1.84 -> 22.99
A21: 20 | E21: 10
A22: 21
A23: 22
A24: 23
A25: 24
A26: 25 | E26: 10
A27: 26
A28: 27 | B28: 34.64 | D28: 30 | E28: 10 | F28: 20
A29: 28
A30: 29
A31: 30
A32: 31
A33: Total | B33: =SUM(B2:B32) -> 83.56 | C33: =SUM(C2:C32) -> 22.99 | D33: =SUM(D2:D32) -> 30 | E33: =SUM(E2:E32) -> 30 | F33: =SUM(F2:F32) -> 20 | G33: =SUM(G2:G32) -> 0 | H33: =SUM(H2:H32) -> 0

Sheet Fevereiro
A1: Dia | B1: Alimentação | C1: Higiene | D1: Combustivel | E1: Viagens | F1: Saídas | G1: Outros | H1: Especificar Outros | K1: Renda: | L1: 250
A2: 1 | B2: 1.85 | E2: =16+1.55 -> 17.55 | I2: =SUM(B2:G2) -> 19.4 | K2: Telecomunicações: | L2: 0
A3: 2 | I3: =SUM(B3:G3) -> 0
A4: 3 | E4: =13.5+5 -> 18.5 | I4: =SUM(B4:G4) -> 18.5
A5: 4 | B5: =9.3+0.25 -> 9.55 | I5: =SUM(B5:G5) -> 9.55
A6: 5 | B6: =1.6+0.25 -> 1.85 | I6: =SUM(B6:G6) -> 1.85
A7: 6 | B7: =1.6+0.25+5.62 -> 7.47 | I7: =SUM(B7:G7) -> 7.47
A8: 7 | B8: =1.6+0.25 -> 1.85 | I8: =SUM(B8:G8) -> 1.85
A9: 8 | B9: =1.6+0.25 -> 1.85 | I9: =SUM(B9:G9) -> 1.85
A10: 9 | F10: 5 | I10: =SUM(B10:G10) -> 5
A11: 10 | B11: 32.36 | G11: 45.96 | H11: sapatilhas e meias | I11: =SUM(B11:G11) -> 78.32
A12: 11 | B12: =1.5+0.25+0.7 -> 2.45 | I12: =SUM(B12:G12) -> 2.45
A13: 12 | B13: 1.75 | I13: =SUM(B13:G13) -> 1.75 | K13: Rendimentos: | L13: 916
A14: 13 | B14: 1.75 | I14: =SUM(B14:G14) -> 1.75 | K14: Despesas: | L14: =SUM(B33:H33)+L1+L2 -> 597.99
A15: 14 | B15: 1.75 | I15: =SUM(B15:G15) -> 1.75
A16: 15 | B16: 0.25 | D16: 20 | E16: 10 | F16: 1.65 | I16: =SUM(B16:G16) -> 31.9 | K16: Saldo: | L16: =L13-L14 -> 318.01
A17: 16 | F17: =1.65+3.65 -> 5.3 | I17: =SUM(B17:G17) -> 5.3
A18: 17 | D18: 40 | E18: 10 | I18: =SUM(B18:G18) -> 50
A19: 18 | B19: 1.75 | I19: =SUM(B19:G19) -> 1.75
A20: 19 | B20: 1.75 | I20: =SUM(B20:G20) -> 1.75
A21: 20 | B21: 4.4 | E21: 6.73 | G21: =28.04+14.08 -> 42.12 | H21: hospital+farmácia | I21: =SUM(B21:G21) -> 53.25
A22: 21 | B22: =0.45+0.25 -> 0.7 | I22: =SUM(B22:G22) -> 0.7
A23: 22 | B23: =0.45+0.25 -> 0.7 | I23: =SUM(B23:G23) -> 0.7
A24: 23 | B24: 16.5 | H24: jantar posta | I24: =SUM(B24:G24) -> 16.5
A25: 24 | B25: =31.1-7 -> 24.1 | G25: 7 | H25: boxers | I25: =SUM(B25:G25) -> 31.1
A26: 25 | B26: 0.7 | I26: =SUM(B26:G26) -> 0.7
A27: 26 | B27: 0.7 | I27: =SUM(B27:G27) -> 0.7
A28: 27 | B28: 1.15 | I28: =SUM(B28:G28) -> 1.15
A29: 28 | B29: 1 | I29: =SUM(B29:G29) -> 1
A30: 29 | I30: =SUM(B30:G30) -> 0
A31: 30 | I31: =SUM(B31:G31) -> 0
A32: 31 | I32: =SUM(B32:G32) -> 0
A33: Total | B33: =SUM(B2:B32) -> 118.18 | C33: =SUM(C2:C32) -> 0 | D33: =SUM(D2:D32) -> 60 | E33: =SUM(E2:E32) -> 62.78 | F33: =SUM(F2:F32) -> 11.95 | G33: =SUM(G2:G32) -> 95.08 | H33: =SUM(H2:H32) -> 0 | I33: =SUM(I2:I32) -> 347.99
K34: +

Sheet Março
A1: Dia | B1: Alimentação | C1: Higiene | D1: Combustivel | E1: Viagens | F1: Saídas | G1: Outros | H1: Especificar Outros | I1: Total | K1: Renda: | L1: 250
A2: 1 | B2: =11.2+0.8 -> 12 | E2: =16+3.51 -> 19.51 | F2: =3.75+4 -> 7.75 | I2: =SUM(B2:G2) -> 39.26 | K2: Telecomunicações:
A3: 2 | B3: 8 | D3: 20 | F3: 15 | G3: =11.9+4 -> 15.9 | H3: fato carnaval garrafa | I3: =SUM(B3:G3) -> 58.9
A4: 3 | E4: =13.5+5 -> 18.5 | I4: =SUM(B4:G4) -> 18.5
A5: 4 | B5: 0.45 | I5: =SUM(B5:G5) -> 0.45
A6: 5 | B6: 0.9 | I6: =SUM(B6:G6) -> 0.9
A7: 6 | B7: =0.25+0.45+0.7 -> 1.4 | I7: =SUM(B7:G7) -> 1.4
A8: 7 | B8: 0.65 | I8: =SUM(B8:G8) -> 0.65
A9: 8 | B9: =0.65+20 -> 20.65 | F9: 3 | G9: 20 | H9: poker | I9: =SUM(B9:G9) -> 43.65
A10: 9 | B10: =18.8-2.25 -> 16.55 | G10: 2.25 | H10: tuppware | I10: =SUM(B10:G10) -> 18.8
A11: 10 | F11: 2 | I11: =SUM(B11:G11) -> 2
A12: 11 | B12: =0.25+0.9 -> 1.15 | D12: 20 | I12: =SUM(B12:G12) -> 21.15
A13: 12 | B13: =0.25+0.3 -> 0.55 | I13: =SUM(B13:G13) -> 0.55 | K13: Rendimentos: | L13: 916
A14: 13 | B14: =0.9+0.25 -> 1.15 | G14: 50 | H14: dentista | I14: =SUM(B14:G14) -> 51.15 | K14: Despesas: | L14: =SUM(B33:H33)+L1+L2 -> 666.18
A15: 14 | B15: =0.25+0.45 -> 0.7 | I15: =SUM(B15:G15) -> 0.7
A16: 15 | E16: 10 | F16: 3.7 | I16: =SUM(B16:G16) -> 13.7 | K16: Saldo: | L16: =L13-L14 -> 249.82
A17: 16 | F17: =7+2.7 -> 9.7 | I17: =SUM(B17:G17) -> 9.7
A18: 17 | D18: 40 | E18: 10 | F18: 1.7 | I18: =SUM(B18:G18) -> 51.7
A19: 18 | B19: =0.25+1.35+2 -> 3.6 | C19: 6 | I19: =SUM(B19:G19) -> 9.6
A20: 19 | B20: =0.25+1.15 -> 1.4 | I20: =SUM(B20:G20) -> 1.4
A21: 20 | B21: =0.25+0.45 -> 0.7 | I21: =SUM(B21:G21) -> 0.7
A22: 21 | B22: =0.7+0.25+0.45 -> 1.4 | I22: =SUM(B22:G22) -> 1.4
A23: 22 | B23: =0.25+0.9 -> 1.15 | F23: 1 | I23: =SUM(B23:G23) -> 2.15
A24: 23 | B24: 8.28 | I24: =SUM(B24:G24) -> 8.28
A25: 24 | F25: 1.3 | I25: =SUM(B25:G25) -> 1.3
A26: 25 | B26: =0.9+0.25+7.87 -> 9.02 | G26: 3 | H26: jornal | I26: =SUM(B26:G26) -> 12.02
A27: 26 | B27: =0.25+0.35 -> 0.6 | G27: 10.91 | H27: futsal | I27: =SUM(B27:G27) -> 11.51
A28: 27 | B28: =0.25+1.35+3.64 -> 5.24 | I28: =SUM(B28:G28) -> 5.24
A29: 28 | B29: =0.25+0.45 -> 0.7 | F29: 1 | I29: =SUM(B29:G29) -> 1.7
A30: 29 | B30: 6.45 | F30: 2.4 | H30: mcdonals | I30: =SUM(B30:G30) -> 8.85
A31: 30 | B31: 0.25 | I31: =SUM(B31:G31) -> 0.25
A32: 31 | B32: =18.62-C32 -> 14.83 | C32: 3.79 | I32: =SUM(B32:G32) -> 18.62
A33: Total | B33: =SUM(B2:B32) -> 117.77 | C33: =SUM(C2:C32) -> 9.79 | D33: =SUM(D2:D32) -> 80 | E33: =SUM(E2:E32) -> 58.01 | F33: =SUM(F2:F32) -> 48.55 | G33: =SUM(G2:G32) -> 102.06 | H33: =SUM(H2:H32) -> 0 | I33: =SUM(B33:G33) -> 416.18

Sheet Maio
A1: Dia | B1: Alimentação | C1: Higiene | D1: Combustivel | E1: Viagens | F1: Saídas | G1: Outros | H1: Especificar Outros | I1: Total | K1: Renda: | L1: 250
A2: 1 | F2: 2.2 | G2: 4.99 | H2: calções | I2: =SUM(B2:H2) -> 7.19 | K2: Telecomunicações:
A3: 2 | B3: =0.45+0.25 -> 0.7 | F3: 1.1 | I3: =SUM(B3:H3) -> 1.8
A4: 3 | B4: =0.25+0.5+0.9 -> 1.65 | I4: =SUM(B4:H4) -> 1.65
A5: 4 | F5: 1.1 | G5: 12 | H5: raquetes+toalha | I5: =SUM(B5:H5) -> 13.1
A6: 5 | B6: 4.52 | D6: 30 | E6: 5.4 | I6: =SUM(B6:H6) -> 39.92
A7: 6 | B7: =0.25+0.4 -> 0.65 | I7: =SUM(B7:H7) -> 0.65
A8: 7 | B8: =0.25+0.9 -> 1.15 | I8: =SUM(B8:H8) -> 1.15
A9: 8 | B9: =0.25+0.4 -> 0.65 | I9: =SUM(B9:H9) -> 0.65
A10: 9 | B10: =0.25+0.4+6.1 -> 6.75 | I10: =SUM(B10:H10) -> 6.75
A11: 10 | B11: =1.65 -> 1.65 | E11: =4.68+9.8 -> 14.48 | F11: 35 | H11: queima | I11: =SUM(B11:H11) -> 51.13
A12: 11 | F12: 9 | H12: erdinger+burger | I12: =SUM(B12:H12) -> 9
A13: 12 | E13: =13.5+5 -> 18.5 | I13: =SUM(B13:H13) -> 18.5 | K13: Rendimentos: | L13: 946.4
A14: 13 | B14: =0.25+1.2 -> 1.45 | I14: =SUM(B14:H14) -> 1.45 | K14: Despesas: | L14: =SUM(B33:H33)+L1+L2 -> 646.19
A15: 14 | B15: =0.25+0.45+3.48 -> 4.18 | I15: =SUM(B15:H15) -> 4.18
A16: 15 | B16: =0.25+0.25+0.35 -> 0.85 | G16: 50 | H16: dentista | I16: =SUM(B16:H16) -> 50.85 | K16: Saldo: | L16: =L13-L14 -> 300.21
A17: 16 | B17: =0.25+0.25+0.85 -> 1.35 | I17: =SUM(B17:H17) -> 1.35
A18: 17 | E18: =10.5 -> 10.5 | F18: 1 | I18: =SUM(B18:H18) -> 11.5
A19: 18 | F19: 30 | H19: benfica campeao | I19: =SUM(B19:H19) -> 30
A20: 19 | E20: =13.5+5 -> 18.5 | I20: =SUM(B20:H20) -> 18.5
A21: 20 | B21: =0.25+0.9 -> 1.15 | F21: 1.1 | I21: =SUM(B21:H21) -> 2.25
A22: 21 | B22: =7.52+0.25+0.45 -> 8.22 | I22: =SUM(B22:H22) -> 8.22
A23: 22 | B23: =0.25+0.25+0.45 -> 0.95 | I23: =SUM(B23:H23) -> 0.95
A24: 23 | B24: =0.25+0.45+0.7 -> 1.4 | I24: =SUM(B24:H24) -> 1.4
A25: 24 | B25: =0.25+0.9+0.7 -> 1.85 | F25: =6.55+6+2.5 -> 15.05 | G25: 2 | H25: braga romana | I25: =SUM(B25:H25) -> 18.9
A26: 25 | B26: =14.51-C26 -> 5.2 | C26: =3.37+3.7+2.24 -> 9.31 | I26: =SUM(B26:H26) -> 14.51
A27: 26 | B27: 4.04 | I27: =SUM(B27:H27) -> 4.04
A28: 27 | B28: =0.25+0.45 -> 0.7 | I28: =SUM(B28:H28) -> 0.7
A29: 28 | B29: =0.25+0.45 -> 0.7 | I29: =SUM(B29:H29) -> 0.7
A30: 29 | B30: =0.25+0.45 -> 0.7 | I30: =SUM(B30:H30) -> 0.7
A31: 30 | B31: =0.25+0.45 -> 0.7 | F31: 1.1 | I31: =SUM(B31:H31) -> 1.8
A32: 31 | B32: =0.25+0.45 -> 0.7 | D32: 40 | F32: =17+15 -> 32 | H32: jantar+rally | I32: =SUM(B32:H32) -> 72.7
A33: Total | B33: =SUM(B2:B32) -> 51.86 | C33: =SUM(C2:C32) -> 9.31 | D33: =SUM(D2:D32) -> 70 | E33: =SUM(E2:E32) -> 67.38 | F33: =SUM(F2:F32) -> 128.65 | G33: =SUM(G2:G32) -> 68.99 | H33: =SUM(H2:H32) -> 0 | I33: =SUM(I2:I32) -> 396.19

Sheet Abril
A1: Dia | B1: Alimentação | C1: Higiene | D1: Combustivel | E1: Viagens | F1: Saídas | G1: Outros | H1: Especificar Outros | I1: Total | K1: Renda: | L1: 250
A2: 1 | B2: =0.9+0.25 -> 1.15 | G2: 12.5 | H2: futsal | I2: =SUM(B2:H2) -> 13.65 | K2: Telecomunicações:
A3: 2 | B3: =0.45+0.25 -> 0.7 | I3: =SUM(B3:H3) -> 0.7
A4: 3 | B4: =0.9+0.25 -> 1.15 | D4: 20 | I4: =SUM(B4:H4) -> 21.15
A5: 4 | I5: =SUM(B5:H5) -> 0
A6: 5 | E6: =16+3.8 -> 19.8 | F6: 25 | H6: c3 | I6: =SUM(B6:H6) -> 44.8
A7: 6 | F7: 2 | I7: =SUM(B7:H7) -> 2
A8: 7 | E8: =13.5+5 -> 18.5 | I8: =SUM(B8:H8) -> 18.5
A9: 8 | B9: =8.34+0.25+1.15 -> 9.74 | I9: =SUM(B9:H9) -> 9.74
A10: 9 | B10: =0.25+0.9+0.7+5.95 -> 7.8 | I10: =SUM(B10:H10) -> 7.8
A11: 10 | B11: =0.25+1.15+0.7+0.77 -> 2.87 | I11: =SUM(B11:H11) -> 2.87
A12: 11 | B12: =0.35+0.4 -> 0.75 | F12: 13.15 | H12: livita | I12: =SUM(B12:H12) -> 13.9
A13: 12 | B13: =0.23+0.9 -> 1.13 | I13: =SUM(B13:H13) -> 1.13 | K13: Rendimentos: | L13: 1060
A14: 13 | B14: 5.95 | G14: =19.98+29.99+36.99 -> 86.96 | H14: mc_calças_sapatilha | I14: =SUM(B14:H14) -> 92.91 | K14: Despesas: | L14: =SUM(B33:H33)+L1+L2 -> 791.4
A15: 14 | F15: 1 | I15: =SUM(B15:H15) -> 1
A16: 15 | B16: 0.9 | I16: =SUM(B16:H16) -> 0.9 | K16: Saldo: | L16: =L13-L14 -> 268.6
A17: 16 | B17: 0.9 | I17: =SUM(B17:H17) -> 0.9
A18: 17 | B18: 1.15 | D18: 40 | G18: 50 | H18: dentista | I18: =SUM(B18:H18) -> 91.15
A19: 18 | B19: =5.95+1.15 -> 7.1 | F19: 2 | I19: =SUM(B19:H19) -> 9.1
A20: 19 | E20: 10 | F20: =1.7+5 -> 6.7 | I20: =SUM(B20:H20) -> 16.7
A21: 20 | F21: =5+1.7 -> 6.7 | I21: =SUM(B21:H21) -> 6.7
A22: 21 | F22: =4+5 -> 9 | I22: =SUM(B22:H22) -> 9
A23: 22 | F23: 2.7 | I23: =SUM(B23:H23) -> 2.7
A24: 23 | F24: =2.7 -> 2.7 | I24: =SUM(B24:H24) -> 2.7
A25: 24 | B25: 15.5 | F25: 64.5 | H25: jantar+garrafa gin | I25: =SUM(B25:H25) -> 80
A26: 25 | D26: 40 | F26: 8.4 | H26: cinema | I26: =SUM(B26:H26) -> 48.4
A27: 26 | F27: 1.7 | I27: =SUM(B27:H27) -> 1.7
A28: 27 | B28: 4.5 | F28: 1.7 | I28: =SUM(B28:H28) -> 6.2
A29: 28 | E29: 10 | F29: 1.2 | I29: =SUM(B29:H29) -> 11.2
A30: 29 | B30: =0.35+12.05 -> 12.4 | I30: =SUM(B30:H30) -> 12.4
A31: 30 | B31: =0.95+10.55 -> 11.5 | H31: degema | I31: =SUM(B31:H31) -> 11.5
A32: 31 | I32: =SUM(B32:H32) -> 0
A33: Total | B33: =SUM(B2:B32) -> 85.19 | C33: =SUM(C2:C32) -> 0 | D33: =SUM(D2:D32) -> 100 | E33: =SUM(E2:E32) -> 58.3 | F33: =SUM(F2:F32) -> 148.45 | G33: =SUM(G2:G32) -> 149.46 | H33: =SUM(H2:H32) -> 0 | I33: =SUM(I2:I32) -> 541.4

Sheet Junho
A1: Dia | B1: Alimentação | C1: Higiene | D1: Combustivel | E1: Viagens | F1: Saídas | G1: Outros | H1: Especificar Outros | I1: Total | K1: Renda: | L1: 250
A2: 1 | I2: =SUM(B2:H2) -> 0 | K2: Telecomunicações:
A3: 2 | B3: =14.86-C3-G3 -> 11.51 | C3: 0.59 | G3: 2.76 | H3: cola | I3: =SUM(B3:H3) -> 14.86
A4: 3 | B4: =0.25+0.75 -> 1 | F4: 13.61 | G4: 22.49 | H4: taberna belga prozis | I4: =SUM(B4:H4) -> 37.1
A5: 4 | B5: =0.25+0.45 -> 0.7 | I5: =SUM(B5:H5) -> 0.7
A6: 5 | B6: =0.25+0.45 -> 0.7 | F6: 2 | G6: . | I6: =SUM(B6:H6) -> 2.7
A7: 6 | B7: =0.25+0.45 -> 0.7 | I7: =SUM(B7:H7) -> 0.7
A8: 7 | B8: =0.25+0.45 -> 0.7 | E8: 10 | F8: =3+1+6.65 -> 10.65 | H8: mac | I8: =SUM(B8:H8) -> 21.35
A9: 8 | F9: =5.8+6+25 -> 36.8 | G9: 20 | H9: figueira+anos jonhy+fisio | I9: =SUM(B9:H9) -> 56.8
A10: 9 | F10: =1.8+4 -> 5.8 | I10: =SUM(B10:H10) -> 5.8
A11: 10 | D11: 50 | E11: 10 | F11: 1.3 | G11: 4.5 | H11: lavar carro | I11: =SUM(B11:H11) -> 65.8
A12: 11 | B12: =0.25+0.9+3.88 -> 5.03 | I12: =SUM(B12:H12) -> 5.03
A13: 12 | B13: =0.25+0.9 -> 1.15 | I13: =SUM(B13:H13) -> 1.15 | K13: Rendimentos: | L13: 916.5
A14: 13 | B14: =0.25+0.9 -> 1.15 | I14: =SUM(B14:H14) -> 1.15 | K14: Despesas: | L14: =SUM(B33:H33)+L1+L2 -> 792.8
A15: 14 | B15: =0.25+1.15 -> 1.4 | F15: 6.55 | H15: mac | I15: =SUM(B15:H15) -> 7.95
A16: 15 | B16: =1.15+0.25 -> 1.4 | I16: =SUM(B16:H16) -> 1.4 | K16: Saldo: | L16: =L13-L14 -> 123.7
A17: 16 | I17: =SUM(B17:H17) -> 0
A18: 17 | B18: =1.15+0.25 -> 1.4 | I18: =SUM(B18:H18) -> 1.4
A19: 18 | B19: =1.15+0.25 -> 1.4 | I19: =SUM(B19:H19) -> 1.4
A20: 19 | B20: =1.15+0.25 -> 1.4 | E20: 9.8 | G20: 50 | H20: dentista | I20: =SUM(B20:H20) -> 61.2
A21: 20 | F21: =1.7+1.7 -> 3.4 | I21: =SUM(B21:H21) -> 3.4
A22: 21 | F22: =1.7+1.7+10 -> 13.4 | G22: 20 | H22: clizone | I22: =SUM(B22:H22) -> 33.4
A23: 22 | B23: 4.5 | F23: =25 -> 25 | I23: =SUM(B23:H23) -> 29.5
A24: 23 | F24: 30 | G24: 93 | H24: relogio | I24: =SUM(B24:H24) -> 123
A25: 24 | E25: =13.5+5 -> 18.5 | I25: =SUM(B25:H25) -> 18.5
A26: 25 | B26: =0.25+1.6+4.97 -> 6.82 | G26: 6.2 | H26: acessorios relogio | I26: =SUM(B26:H26) -> 13.02
A27: 26 | B27: =1.15+0.25 -> 1.4 | I27: =SUM(B27:H27) -> 1.4
A28: 27 | B28: =1.15+0.25 -> 1.4 | G28: 0 | H28: revolut | I28: =SUM(B28:H28) -> 1.4
A29: 28 | B29: =1.15+0.25 -> 1.4 | F29: =4+7 -> 11 | I29: =SUM(B29:H29) -> 12.4
A30: 29 | B30: 20.29 | I30: =SUM(B30:H30) -> 20.29
A31: 30 | I31: =SUM(B31:H31) -> 0
A32: 31 | I32: =SUM(B32:H32) -> 0
A33: Total | B33: =SUM(B2:B32) -> 65.45 | C33: =SUM(C2:C32) -> 0.59 | D33: =SUM(D2:D32) -> 50 | E33: =SUM(E2:E32) -> 48.3 | F33: =SUM(F2:F32) -> 159.51 | G33: =SUM(G2:G32) -> 218.95 | H33: =SUM(H2:H32) -> 0 | I33: =SUM(I2:I32) -> 542.8

Sheet Julho
A1: Dia | B1: Alimentação | C1: Higiene | D1: Combustivel | E1: Viagens | F1: Saídas | G1: Outros | H1: Especificar Outros | I1: Total | K1: Renda: | L1: =56.5+217 -> 273.5
A2: 1 | B2: =0.25 -> 0.25 | F2: 1.1 | I2: =SUM(B2:H2) -> 1.35 | K2: Despesas(ALGT): | L2: 0
A3: 2 | B3: =0.25+1.15 -> 1.4 | I3: =SUM(B3:H3) -> 1.4 | K3: Telecomunicações:
A4: 3 | B4: =0.25+1.15 -> 1.4 | I4: =SUM(B4:H4) -> 1.4
A5: 4 | B5: =1.4 -> 1.4 | F5: =2+19.5+3.5 -> 25 | H5: posta | I5: =SUM(B5:H5) -> 26.4
A6: 5 | B6: =1.4 -> 1.4 | I6: =SUM(B6:H6) -> 1.4
A7: 6 | G7: =105 -> 105 | H7: casaco+calçoes | I7: =SUM(B7:H7) -> 105
A8: 7 | B8: =0.77+1.59+1.39 -> 3.75 | C8: =13.1-B8 -> 9.35 | I8: =SUM(B8:H8) -> 13.1
A9: 8 | B9: =0.25+1.6 -> 1.85 | I9: =SUM(B9:H9) -> 1.85
A10: 9 | B10: =0.25+1.15 -> 1.4 | I10: =SUM(B10:H10) -> 1.4
A11: 10 | B11: =B10+0.8 -> 2.2 | I11: =SUM(B11:H11) -> 2.2
A12: 11 | B12: =1.6+0.7 -> 2.3 | D12: 20 | I12: =SUM(B12:H12) -> 22.3
A13: 12 | B13: =0.25+1.15+6.55 -> 7.95 | E13: 10 | F13: =2+2 -> 4 | H13: mac | I13: =SUM(B13:H13) -> 21.95 | K13: Rendimentos: | L13: 1842.15 | M13: sub ferias
A14: 13 | F14: 13 | I14: =SUM(B14:H14) -> 13 | K14: Despesas: | L14: =SUM(B33:H33)+L1+L2+L3 -> 784.83
A15: 14 | D15: 30 | E15: 10 | I15: =SUM(B15:H15) -> 40
A16: 15 | B16: =1.15+0.25+0.7 -> 2.1 | I16: =SUM(B16:H16) -> 2.1 | K16: Saldo: | L16: =L13-L14 -> 1057.32
A17: 16 | B17: =B16+(15.81-C17-G17) -> 11.97 | C17: 1.95 | G17: 3.99 | H17: liq carro+vassoura | I17: =SUM(B17:H17) -> 17.91
A18: 17 | B18: =0.25+1.15 -> 1.4 | G18: 50 | H18: dentista | I18: =SUM(B18:H18) -> 51.4
A19: 18 | B19: =1.4 -> 1.4 | I19: =SUM(B19:H19) -> 1.4
A20: 19 | B20: =1.4 -> 1.4 | F20: =24.5+6+3 -> 33.5 | H20: jacó | I20: =SUM(B20:H20) -> 34.9
A21: 20 | B21: 13.92 | D21: 16 | F21: 2.8 | I21: =SUM(B21:H21) -> 32.72
A22: 21 | F22: 20 | G22: 2.2 | H22: bo-zen + piscina | I22: =SUM(B22:H22) -> 22.2
A23: 22 | B23: =0.25+0.7+1.15 -> 2.1 | I23: =SUM(B23:H23) -> 2.1
A24: 23 | B24: =0.25+0.7+1.6 -> 2.55 | I24: =SUM(B24:H24) -> 2.55
A25: 24 | B25: =B23 -> 2.1 | I25: =SUM(B25:H25) -> 2.1
A26: 25 | I26: =SUM(B26:H26) -> 0
A27: 26 | E27: 10.5 | F27: 17 | H27: expo | I27: =SUM(B27:H27) -> 27.5
A28: 27 | F28: =14+20 -> 34 | H28: expo+c3 | I28: =SUM(B28:H28) -> 34
A29: 28 | E29: =13.5+4.2 -> 17.7 | I29: =SUM(B29:H29) -> 17.7
A30: 29 | B30: =1.6+0.7 -> 2.3 | F30: 4 | I30: =SUM(B30:H30) -> 6.3
A31: 30 | B31: =1.15+0.7 -> 1.85 | I31: =SUM(B31:H31) -> 1.85
A32: 31 | B32: =1.15+0.7 -> 1.85 | I32: =SUM(B32:H32) -> 1.85
A33: Total | B33: =SUM(B2:B32) -> 70.24 | C33: =SUM(C2:C32) -> 11.3 | D33: =SUM(D2:D32) -> 66 | E33: =SUM(E2:E32) -> 48.2 | F33: =SUM(F2:F32) -> 154.4 | G33: =SUM(G2:G32) -> 161.19 | H33: =SUM(H2:H32) -> 0 | I33: =SUM(I2:I32) -> 511.33

Sheet Agosto
A1: Dia | B1: Alimentação | C1: Higiene | D1: Combustivel | E1: Viagens | F1: Saídas | G1: Outros | H1: Especificar Outros | I1: Total | K1: Renda: | L1: 217
A2: 1 | B2: =0.25+1.15+0.7 -> 2.1 | I2: =SUM(B2:H2) -> 2.1 | K2: Despesas(ALGT): | L2: 50.5
A3: 2 | B3: =6.55+0.25+1.6 -> 8.4 | D3: 20 | E3: 10 | F3: 10 | I3: =SUM(B3:H3) -> 48.4 | K3: Telecomunicações:
A4: 3 | B4: 2.2 | F4: 17 | I4: =SUM(B4:H4) -> 19.2
A5: 4 | B5: 2 | D5: 15 | I5: =SUM(B5:H5) -> 17
A6: 5 | B6: =1.6+0.7 -> 2.3 | I6: =SUM(B6:H6) -> 2.3
A7: 6 | B7: 1.4 | I7: =SUM(B7:H7) -> 1.4
A8: 7 | B8: 1.4 | I8: =SUM(B8:H8) -> 1.4
A9: 8 | B9: 1.4 | I9: =SUM(B9:H9) -> 1.4
A10: 9 | B10: =1.4+6.55 -> 7.95 | D10: 40 | E10: 10 | F10: 2 | I10: =SUM(B10:H10) -> 59.95
A11: 10 | B11: 24 | I11: =SUM(B11:H11) -> 24
A12: 11 | B12: 5 | F12: =60-B13-B12 -> 42 | I12: =SUM(B12:H12) -> 47
A13: 12 | B13: 13 | I13: =SUM(B13:H13) -> 13 | K13: Rendimentos: | L13: 916.5
A14: 13 | I14: =SUM(B14:H14) -> 0 | K14: Despesas: | L14: =SUM(B33:H33)+L1+L2 -> 1316.32
A15: 14 | F15: 60 | G15: 350 | H15: aparelho | I15: =SUM(B15:H15) -> 410
A16: 15 | F16: 30 | I16: =SUM(B16:H16) -> 30 | K16: Saldo: | L16: =L13-L14 -> -399.82
A17: 16 | I17: =SUM(B17:H17) -> 0
A18: 17 | B18: 6.5 | F18: =70-B18-50-5-10 -> -1.5 | I18: =SUM(B18:H18) -> 5 | J18: =SUM(I10:I18)-350 -> 238.95
A19: 18 | G19: =240-25.5 -> 214.5 | H19: casa | I19: =SUM(B19:H19) -> 214.5
A20: 19 | B20: 1.9 | F20: 7 | G20: 7 | I20: =SUM(B20:H20) -> 15.9
A21: 20 | B21: 2.9 | I21: =SUM(B21:H21) -> 2.9
A22: 21 | F22: 3.3 | I22: =SUM(B22:H22) -> 3.3
A23: 22 | B23: 1.9 | I23: =SUM(B23:H23) -> 1.9
A24: 23 | B24: 1.9 | F24: 20 | I24: =SUM(B24:H24) -> 21.9
A25: 24 | B25: 2 | F25: 3 | I25: =SUM(B25:H25) -> 5
A26: 25 | E26: 10 | F26: 1 | I26: =SUM(B26:H26) -> 11
A27: 26 | B27: =1.6+9.59+4.68 -> 15.87 | G27: 6 | I27: =SUM(B27:H27) -> 21.87
A28: 27 | B28: 1.6 | I28: =SUM(B28:H28) -> 1.6
A29: 28 | B29: 1.6 | I29: =SUM(B29:H29) -> 1.6
A30: 29 | B30: 1.6 | I30: =SUM(B30:H30) -> 1.6
A31: 30 | B31: 1.6 | I31: =SUM(B31:H31) -> 1.6
A32: 31 | B32: =31+5 -> 36 | E32: 2 | F32: 24 | I32: =SUM(B32:H32) -> 62
A33: Total | B33: =SUM(B2:B32) -> 146.52 | C33: =SUM(C2:C32) -> 0 | D33: =SUM(D2:D32) -> 75 | E33: =SUM(E2:E32) -> 32 | F33: =SUM(F2:F32) -> 217.8 | G33: =SUM(G2:G32) -> 577.5 | H33: =SUM(H2:H32) -> 0 | I33: =SUM(B33:H33) -> 1048.82

Sheet Setembro
A1: Dia | B1: Alimentação | C1: Higiene | D1: Combustivel | E1: Viagens | F1: Saídas | G1: Outros | H1: Especificar Outros | I1: Total | K1: Renda: | L1: 217
A2: 1 | I2: =SUM(B2:H2) -> 0 | K2: Despesas(ALGT): | L2: =257-L1 -> 40
A3: 2 | B3: =0.25+1.15+0.7 -> 2.1 | I3: =SUM(B3:H3) -> 2.1 | K3: Telecomunicações:
A4: 3 | B4: =0.25+1.15+0.7 -> 2.1 | I4: =SUM(B4:H4) -> 2.1
A5: 4 | B5: =0.25+1.15 -> 1.4 | I5: =SUM(B5:H5) -> 1.4
A6: 5 | B6: =0.25+1.15 -> 1.4 | I6: =SUM(B6:H6) -> 1.4
A7: 6 | B7: =0.25+1.15+5 -> 6.4 | F7: =25+17 -> 42 | I7: =SUM(B7:H7) -> 48.4
A8: 7 | B8: =5.5+1.5 -> 7 | F8: 5 | I8: =SUM(B8:H8) -> 12
A9: 8 | I9: =SUM(B9:H9) -> 0
A10: 9 | B10: =1.4+19.42 -> 20.82 | H10: continente | I10: =SUM(B10:H10) -> 20.82
A11: 10 | B11: =1.4 -> 1.4 | I11: =SUM(B11:H11) -> 1.4
A12: 11 | B12: =1.4+1.49 -> 2.89 | G12: 50 | H12: dentista | I12: =SUM(B12:H12) -> 52.89
A13: 12 | B13: =1.4+13.1 -> 14.5 | D13: 15 | F13: 1.5 | H13: canudo | I13: =SUM(B13:H13) -> 31 | K13: Rendimentos: | L13: 927.26
A14: 13 | B14: =1.4 -> 1.4 | E14: 9.8 | F14: 4 | I14: =SUM(B14:H14) -> 15.2 | K14: Despesas: | L14: =SUM(B33:H33)+L1+L2 -> 648.55
A15: 14 | F15: =20+15+5 -> 40 | H15: praia | I15: =SUM(B15:H15) -> 40
A16: 15 | B16: 0.8 | E16: =13.5+4.2 -> 17.7 | I16: =SUM(B16:H16) -> 18.5 | K16: Saldo: | L16: =L13-L14 -> 278.71
A17: 16 | B17: =1.6+0.25+1.49 -> 3.34 | C17: 3.29 | I17: =SUM(B17:H17) -> 6.63
A18: 17 | B18: =0.25+1.15+0.7 -> 2.1 | I18: =SUM(B18:H18) -> 2.1
A19: 18 | B19: =0.25+1.15+0.7 -> 2.1 | I19: =SUM(B19:H19) -> 2.1
A20: 19 | B20: =0.25+1.15+0.7 -> 2.1 | G20: 30 | H20: consulta joelho | I20: =SUM(B20:H20) -> 32.1
A21: 20 | B21: =0.25+1.15+0.7+5.95 -> 8.05 | F21: 6 | I21: =SUM(B21:H21) -> 14.05
A22: 21 | I22: =SUM(B22:H22) -> 0
A23: 22 | B23: =39.59-C23 -> 28.72 | C23: =2.99+4.99+2.89 -> 10.87 | I23: =SUM(B23:H23) -> 39.59
A24: 23 | B24: =0.25+1.15 -> 1.4 | I24: =SUM(B24:H24) -> 1.4
A25: 24 | B25: =0.25+1.15 -> 1.4 | G25: 10 | H25: trotinetes | I25: =SUM(B25:H25) -> 11.4
A26: 25 | B26: =B25 -> 1.4 | I26: =SUM(B26:H26) -> 1.4
A27: 26 | B27: =B26 -> 1.4 | I27: =SUM(B27:H27) -> 1.4
A28: 27 | B28: =B27+6.95 -> 8.35 | F28: 2 | H28: mac | I28: =SUM(B28:H28) -> 10.35
A29: 28 | B29: 9.5 | F29: 6 | H29: vegan | I29: =SUM(B29:H29) -> 15.5
A30: 29 | B30: =0.95+0.97 -> 1.92 | F30: 3 | I30: =SUM(B30:H30) -> 4.92
A31: 30 | B31: 1.4 | I31: =SUM(B31:H31) -> 1.4
A32: 31 | I32: =SUM(B32:H32) -> 0
A33: Total | B33: =SUM(B2:B32) -> 135.39 | C33: =SUM(C2:C32) -> 14.16 | D33: =SUM(D2:D32) -> 15 | E33: =SUM(E2:E32) -> 27.5 | F33: =SUM(F2:F32) -> 109.5 | G33: =SUM(G2:G32) -> 90 | H33: =SUM(H2:H32) -> 0 | I33: =SUM(I2:I32) -> 391.55
B35: 0

Sheet Outubro
A1: Dia | B1: Alimentação | C1: Higiene | D1: Combustivel | E1: Viagens | F1: Saídas | G1: Outros | H1: Especificar Outros | I1: Total | K1: Renda: | L1: 217
A2: 1 | B2: 1.4 | I2: =SUM(B2:H2) -> 1.4 | K2: Despesas(ALGT): | L2: =262-L1 -> 45
A3: 2 | B3: =1.4+1 -> 2.4 | D3: 15 | F3: 6 | I3: =SUM(B3:H3) -> 23.4 | K3: Telecomunicações: | L3: 13
A4: 3 | B4: =0.25+1.15+0.25 -> 1.65 | E4: 10 | F4: 1 | I4: =SUM(B4:H4) -> 12.65
A5: 4 | B5: 2 | C5: 6 | F5: =1.9+7.4 -> 9.3 | I5: =SUM(B5:H5) -> 17.3
A6: 5 | B6: 2.4 | F6: =2.5+3 -> 5.5 | I6: =SUM(B6:H6) -> 7.9
A7: 6 | D7: 30 | E7: =10-10 -> 0 | F7: 1.9 | I7: =SUM(B7:H7) -> 31.9
A8: 7 | B8: =1.4 -> 1.4 | G8: =22.36+14.23 -> 36.59 | H8: prozis; gearbest | I8: =SUM(B8:H8) -> 37.99
A9: 8 | B9: =1.4+7.1 -> 8.5 | I9: =SUM(B9:H9) -> 8.5
A10: 9 | B10: 1.4 | G10: =7.5+60 -> 67.5 | H10: telemovel+sapatilhas | I10: =SUM(B10:H10) -> 68.9
A11: 10 | B11: =1.4+3.3 -> 4.7 | F11: 1.2 | G11: 2.5 | I11: =SUM(B11:H11) -> 8.4
A12: 11 | B12: 1.4 | F12: =3+21.1+9+2.5+1.5 -> 37.1 | H12: posta+ba | I12: =SUM(B12:H12) -> 38.5
A13: 12 | I13: =SUM(B13:H13) -> 0 | K13: Rendimentos: | L13: 916
A14: 13 | B14: =37.96-F14-C14 -> 30.76 | C14: 2.9 | F14: 4.3 | I14: =SUM(B14:H14) -> 37.96 | K14: Despesas: | L14: =SUM(B33:H33)+L1+L2+L3 -> 851.2
A15: 14 | B15: =1.4+0.7 -> 2.1 | I15: =SUM(B15:H15) -> 2.1
A16: 15 | B16: =1.4 -> 1.4 | I16: =SUM(B16:H16) -> 1.4 | K16: Saldo: | L16: =L13-L14 -> 64.8
A17: 16 | B17: =B16 -> 1.4 | F17: 5 | I17: =SUM(B17:H17) -> 6.4
A18: 17 | B18: =B17 -> 1.4 | G18: =15+30 -> 45 | H18: consulta+medic | I18: =SUM(B18:H18) -> 46.4
A19: 18 | B19: =B18 -> 1.4 | D19: 30 | E19: 10 | F19: =7.3+8+3 -> 18.3 | I19: =SUM(B19:H19) -> 59.7
A20: 19 | F20: 4.5 | I20: =SUM(B20:H20) -> 4.5
A21: 20 | E21: -10 | I21: =SUM(B21:H21) -> -10
A22: 21 | B22: 1.4 | I22: =SUM(B22:H22) -> 1.4
A23: 22 | B23: 1.4 | I23: =SUM(B23:H23) -> 1.4
A24: 23 | B24: 1.4 | G24: 50 | H24: dentista | I24: =SUM(B24:H24) -> 51.4
A25: 24 | B25: =1.4+15 -> 16.4 | I25: =SUM(B25:H25) -> 16.4
A26: 25 | B26: =1.4+7.1 -> 8.5 | D26: 15 | F26: 2 | I26: =SUM(B26:H26) -> 25.5
A27: 26 | B27: 10 | E27: 6.6 | F27: =3.5+15 -> 18.5 | I27: =SUM(B27:H27) -> 35.1
A28: 27 | B28: 7.5 | I28: =SUM(B28:H28) -> 7.5
A29: 28 | B29: =1.4 -> 1.4 | I29: =SUM(B29:H29) -> 1.4
A30: 29 | B30: 1.4 | I30: =SUM(B30:H30) -> 1.4
A31: 30 | B31: 1.4 | G31: 8.6 | H31: disfarce hallowen | I31: =SUM(B31:H31) -> 10
A32: 31 | B32: 1.4 | E32: 10 | F32: 8 | I32: =SUM(B32:H32) -> 19.4
A33: Total | B33: =SUM(B2:B32) -> 117.91 | C33: =SUM(C2:C32) -> 8.9 | D33: =SUM(D2:D32) -> 90 | E33: =SUM(E2:E32) -> 26.6 | F33: =SUM(F2:F32) -> 122.6 | G33: =SUM(G2:G32) -> 210.19 | H33: =SUM(H2:H32) -> 0 | I33: =SUM(I2:I32) -> 576.2

Sheet Novembro
A1: Dia | B1: Alimentação | C1: Higiene | D1: Combustivel | E1: Viagens | F1: Saídas | G1: Outros | H1: Especificar Outros | I1: Total | K1: Renda: | L1: 217
A2: 1 | F2: 5 | I2: =SUM(B2:H2) -> 5 | K2: Despesas(ALGT): | L2: =253-L1 -> 36
A3: 2 | F3: 1.2 | I3: =SUM(B3:H3) -> 1.2 | K3: Telecomunicações: | L3: 13
A4: 3 | D4: 20 | E4: 0 | G4: 76.49 | H4: fifa+comando | I4: =SUM(B4:H4) -> 96.49
A5: 4 | B5: 1.4 | G5: 11.75 | H5: futsal | I5: =SUM(B5:H5) -> 13.15
A6: 5 | B6: =1.4+0.75 -> 2.15 | G6: =15+2 -> 17 | H6: consulta | I6: =SUM(B6:H6) -> 19.15
A7: 6 | B7: =1.4+0.75+2.15 -> 4.3 | I7: =SUM(B7:H7) -> 4.3
A8: 7 | B8: =1.4+0.75 -> 2.15 | G8: 27.5 | H8: tac | I8: =SUM(B8:H8) -> 29.65
A9: 8 | B9: =1.4+0.75+6 -> 8.15 | F9: 3 | I9: =SUM(B9:H9) -> 11.15
A10: 9 | B10: 23.21 | I10: =SUM(B10:H10) -> 23.21
A11: 10 | I11: =SUM(B11:H11) -> 0
A12: 11 | B12: 1.4 | I12: =SUM(B12:H12) -> 1.4
A13: 12 | B13: 1.4 | G13: 15 | H13: consulta | I13: =SUM(B13:H13) -> 16.4 | K13: Rendimentos: | L13: 1795
A14: 13 | B14: 1.4 | I14: =SUM(B14:H14) -> 1.4 | K14: Despesas: | L14: =SUM(B33:H33)+L1+L2+L3 -> 877
A15: 14 | B15: 1.4 | I15: =SUM(B15:H15) -> 1.4
A16: 15 | B16: =1.4+7 -> 8.4 | F16: 5 | I16: =SUM(B16:H16) -> 13.4 | K16: Saldo: | L16: =L13-L14 -> 918
A17: 16 | B17: 23 | F17: =17+5 -> 22 | G17: =8+17+15 -> 40 | H17: roupa+prenda | I17: =SUM(B17:H17) -> 85
A18: 17 | I18: =SUM(B18:H18) -> 0
A19: 18 | B19: 1.4 | I19: =SUM(B19:H19) -> 1.4
A20: 19 | B20: =1.4+0.65 -> 2.05 | I20: =SUM(B20:H20) -> 2.05
A21: 20 | B21: =1.4+0.65 -> 2.05 | G21: 50 | H21: dentista | I21: =SUM(B21:H21) -> 52.05
A22: 21 | B22: =1.4+0.65 -> 2.05 | D22: 20 | E22: 10 | I22: =SUM(B22:H22) -> 32.05
A23: 22 | I23: =SUM(B23:H23) -> 0
A24: 23 | F24: =50+3.7 -> 53.7 | G24: 31 | H24: inspcção | I24: =SUM(B24:H24) -> 84.7
A25: 24 | D25: 20 | E25: 10 | I25: =SUM(B25:H25) -> 30
A26: 25 | B26: =1.4+0.65 -> 2.05 | G26: 45 | H26: ps4 plus | I26: =SUM(B26:H26) -> 47.05
A27: 26 | B27: =B26 -> 2.05 | I27: =SUM(B27:H27) -> 2.05
A28: 27 | B28: =B27 -> 2.05 | I28: =SUM(B28:H28) -> 2.05
A29: 28 | B29: 0.9 | I29: =SUM(B29:H29) -> 0.9
A30: 29 | B30: 0.9 | F30: 1 | G30: 20 | H30: gorro | I30: =SUM(B30:H30) -> 21.9
A31: 30 | B31: =7.21+5.29 -> 12.5 | I31: =SUM(B31:H31) -> 12.5
A32: 31 | I32: =SUM(B32:H32) -> 0
A33: Total | B33: =SUM(B2:B32) -> 106.36 | C33: =SUM(C2:C32) -> 0 | D33: =SUM(D2:D32) -> 60 | E33: =SUM(E2:E32) -> 20 | F33: =SUM(F2:F32) -> 90.9 | G33: =SUM(G2:G32) -> 333.74 | H33: =SUM(H2:H32) -> 0 | I33: =SUM(I2:I32) -> 611

Sheet Dezembro
A1: Dia | B1: Alimentação | C1: Higiene | D1: Combustivel | E1: Viagens | F1: Saídas | G1: Outros | H1: Especificar Outros | I1: Total | K1: Renda: | L1: 217
A2: 1 | B2: 15 | I2: =SUM(B2:H2) -> 15 | K2: Despesas(ALGT): | L2: =267.6-L1 -> 50.6
A3: 2 | B3: =0.25+1.15 -> 1.4 | I3: =SUM(B3:H3) -> 1.4 | K3: Telecomunicações: | L3: 13
A4: 3 | B4: =0.25+1.15 -> 1.4 | I4: =SUM(B4:H4) -> 1.4
A5: 4 | B5: =0.25+1.15 -> 1.4 | I5: =SUM(B5:H5) -> 1.4
A6: 5 | B6: =0.25+1.15 -> 1.4 | I6: =SUM(B6:H6) -> 1.4
A7: 6 | B7: =0.25+1.15 -> 1.4 | E7: =11.2+7.1 -> 18.3 | I7: =SUM(B7:H7) -> 19.7
A8: 7 | G8: 9 | H8: v.porto | I8: =SUM(B8:H8) -> 9
A9: 8 | E9: =13.5+4.2 -> 17.7 | I9: =SUM(B9:H9) -> 17.7
A10: 9 | B10: 1.4 | I10: =SUM(B10:H10) -> 1.4
A11: 10 | B11: 1.4 | I11: =SUM(B11:H11) -> 1.4
A12: 11 | B12: 1.4 | I12: =SUM(B12:H12) -> 1.4
A13: 12 | B13: =1.4+7.25 -> 8.65 | I13: =SUM(B13:H13) -> 8.65 | K13: Rendimentos: | L13: =916.5+200 -> 1116.5
A14: 13 | B14: =1.4+1.6 -> 3 | E14: 3.5 | F14: 22 | H14: jantar bosch | I14: =SUM(B14:H14) -> 28.5 | K14: Despesas: | L14: =SUM(B33:H33)+L1+L2+L3 -> 946.48
A15: 14 | B15: =6.5+21.4 -> 27.9 | I15: =SUM(B15:H15) -> 27.9
A16: 15 | B16: 3.4 | I16: =SUM(B16:H16) -> 3.4 | K16: Saldo: | L16: =L13-L14 -> 170.02
A17: 16 | B17: =1.4+0.7 -> 2.1 | I17: =SUM(B17:H17) -> 2.1
A18: 17 | B18: =1.4 -> 1.4 | I18: =SUM(B18:H18) -> 1.4
A19: 18 | B19: =1.4+7 -> 8.4 | G19: 50 | H19: pizza+dentista | I19: =SUM(B19:H19) -> 58.4
A20: 19 | B20: 1.4 | F20: 3 | I20: =SUM(B20:H20) -> 4.4
A21: 20 | B21: 1.4 | G21: =4+8+21.47+14.28+26+5 -> 78.75 | H21: prendas+camisola | I21: =SUM(B21:H21) -> 80.15
A22: 21 | E22: 10 | G22: 56 | H22: airpods | I22: =SUM(B22:H22) -> 66
A23: 22 | D23: 20 | F23: 2.7 | I23: =SUM(B23:H23) -> 22.7
A24: 23 | B24: =3 -> 3 | F24: 5 | G24: =90 -> 90 | H24: casaco | I24: =SUM(B24:H24) -> 98
A25: 24 | F25: 3 | I25: =SUM(B25:H25) -> 3
A26: 25 | F26: 4 | I26: =SUM(B26:H26) -> 4
A27: 26 | B27: 3 | E27: 30 | F27: 2 | I27: =SUM(B27:H27) -> 35
A28: 27 | F28: 2 | I28: =SUM(B28:H28) -> 2
A29: 28 | F29: 3 | I29: =SUM(B29:H29) -> 3
A30: 29 | F30: 3 | I30: =SUM(B30:H30) -> 3
A31: 30 | F31: 2 | I31: =SUM(B31:H31) -> 2
A32: 31 | B32: 11.08 | F32: =50+45 -> 95 | G32: =25+10 -> 35 | I32: =SUM(B32:H32) -> 141.08
A33: Total | B33: =SUM(B2:B32) -> 100.93 | C33: =SUM(C2:C32) -> 0 | D33: =SUM(D2:D32) -> 20 | E33: =SUM(E2:E32) -> 79.5 | F33: =SUM(F2:F32) -> 146.7 | G33: =SUM(G2:G32) -> 318.75 | H33: =SUM(H2:H32) -> 0 | I33: =SUM(I2:I32) -> 665.88
